<?xml version='1.0' encoding='UTF-8' standalone='yes' ?>
<!--File Created By SMS Backup & Restore v10.16.001 on 11/05/2022 02:34:34-->
<!--

To view this file in a more readable format, visit https://synctech.com.au/view-backup/

-->
<smses count="195" backup_set="b7db8a0d-b8f6-49a9-b0f9-7dcf78c98257" backup_date="1652225667951" type="full">
  <sms protocol="0" address="Whatsapp" date="1650272600000" type="1" subject="null" body="&lt;#&gt; WhatsApp kod: 247-987&#13;&#10;&#13;&#10;Dogrula: v.whatsapp.com/247987&#13;&#10;&#13;&#10;Kodu paylasmayin&#13;&#10;4sgLq1p5sV6 B273" toa="null" sc_toa="null" service_center="null" read="1" status="-1" locked="0" date_sent="0" sub_id="-1" readable_date="18 Nis 2022 12:03:20" contact_name="(Unknown)" />
  <sms protocol="0" address="Whatsapp" date="1650272600000" type="1" subject="null" body="&lt;#&gt; WhatsApp kod: 247-987&#13;&#10;&#13;&#10;Dogrula: v.whatsapp.com/247987&#13;&#10;&#13;&#10;Kodu paylasmayin&#13;&#10;4sgLq1p5sV6 B273" toa="null" sc_toa="null" service_center="null" read="1" status="-1" locked="0" date_sent="0" sub_id="-1" readable_date="18 Nis 2022 12:03:20" contact_name="(Unknown)" />
  <sms protocol="0" address="Whatsapp" date="1650272600378" type="1" subject="null" body="&lt;#&gt; WhatsApp kod: 247-987&#10;&#10;Dogrula: v.whatsapp.com/247987&#10;&#10;Kodu paylasmayin&#10;4sgLq1p5sV6 B273" toa="null" sc_toa="null" service_center="+908502740878" read="1" status="-1" locked="0" date_sent="1650272599000" sub_id="1" readable_date="18 Nis 2022 12:03:20" contact_name="(Unknown)" />
  <sms protocol="0" address="600653000000" date="1650274463000" type="1" subject="null" body="G-056323, Google doğrulama kodunuzdur." toa="null" sc_toa="null" service_center="null" read="1" status="-1" locked="0" date_sent="0" sub_id="-1" readable_date="18 Nis 2022 12:34:23" contact_name="(Unknown)" />
  <sms protocol="0" address="600653000000" date="1650274463000" type="1" subject="null" body="G-056323, Google doğrulama kodunuzdur." toa="null" sc_toa="null" service_center="null" read="1" status="-1" locked="0" date_sent="0" sub_id="-1" readable_date="18 Nis 2022 12:34:23" contact_name="(Unknown)" />
  <sms protocol="0" address="600653000000" date="1650274463696" type="1" subject="null" body="G-056323, Google doğrulama kodunuzdur." toa="null" sc_toa="null" service_center="+320335210101" read="1" status="-1" locked="0" date_sent="1650274462000" sub_id="1" readable_date="18 Nis 2022 12:34:23" contact_name="(Unknown)" />
  <sms protocol="0" address="+905428500930" date="1650292143000" type="1" subject="null" body="BUGUNE OZEL UYELIGINIZE GIRIS YAPIP BENI ARA KISMINDAN ARAMA TALEP EDIN %100 - 1.000 TL CEVRIMSIZ BONUS KAZANIN, HER GUN %100 BONUS FIRSATI : www.onwin387.com" toa="null" sc_toa="null" service_center="null" read="1" status="-1" locked="0" date_sent="0" sub_id="-1" readable_date="18 Nis 2022 17:29:03" contact_name="(Unknown)" />
  <sms protocol="0" address="+905428500930" date="1650292143000" type="1" subject="null" body="BUGUNE OZEL UYELIGINIZE GIRIS YAPIP BENI ARA KISMINDAN ARAMA TALEP EDIN %100 - 1.000 TL CEVRIMSIZ BONUS KAZANIN, HER GUN %100 BONUS FIRSATI : www.onwin387.com" toa="null" sc_toa="null" service_center="null" read="1" status="-1" locked="0" date_sent="0" sub_id="-1" readable_date="18 Nis 2022 17:29:03" contact_name="(Unknown)" />
  <sms protocol="0" address="+905428500930" date="1650292143112" type="1" subject="null" body="BUGUNE OZEL UYELIGINIZE GIRIS YAPIP BENI ARA KISMINDAN ARAMA TALEP EDIN %100 - 1.000 TL CEVRIMSIZ BONUS KAZANIN, HER GUN %100 BONUS FIRSATI : www.onwin387.com" toa="null" sc_toa="null" service_center="+908504140500" read="1" status="-1" locked="0" date_sent="1650292142000" sub_id="1" readable_date="18 Nis 2022 17:29:03" contact_name="(Unknown)" />
  <sms protocol="0" address="PAPARA" date="1650297305000" type="1" subject="null" body="Papara giris sifreniz 387247. KIMSEYLE PAYLASMAYINIZ. B002" toa="null" sc_toa="null" service_center="null" read="1" status="-1" locked="0" date_sent="0" sub_id="-1" readable_date="18 Nis 2022 18:55:05" contact_name="(Unknown)" />
  <sms protocol="0" address="PAPARA" date="1650297305000" type="1" subject="null" body="Papara giris sifreniz 387247. KIMSEYLE PAYLASMAYINIZ. B002" toa="null" sc_toa="null" service_center="null" read="1" status="-1" locked="0" date_sent="0" sub_id="-1" readable_date="18 Nis 2022 18:55:05" contact_name="(Unknown)" />
  <sms protocol="0" address="PAPARA" date="1650297305325" type="1" subject="null" body="Papara giris sifreniz 387247. KIMSEYLE PAYLASMAYINIZ. B002" toa="null" sc_toa="null" service_center="+905329043410" read="1" status="-1" locked="0" date_sent="1650297304000" sub_id="1" readable_date="18 Nis 2022 18:55:05" contact_name="(Unknown)" />
  <sms protocol="0" address="Snapchat" date="1650305871000" type="1" subject="null" body="&lt;#&gt; Snapchat Kodu: 879273. İyi Snap'leşmeler! qunyt57f5Rf B043" toa="null" sc_toa="null" service_center="null" read="1" status="-1" locked="0" date_sent="0" sub_id="-1" readable_date="18 Nis 2022 21:17:51" contact_name="(Unknown)" />
  <sms protocol="0" address="Snapchat" date="1650305871000" type="1" subject="null" body="&lt;#&gt; Snapchat Kodu: 879273. İyi Snap'leşmeler! qunyt57f5Rf B043" toa="null" sc_toa="null" service_center="null" read="1" status="-1" locked="0" date_sent="0" sub_id="-1" readable_date="18 Nis 2022 21:17:51" contact_name="(Unknown)" />
  <sms protocol="0" address="7529" date="1650322234000" type="2" subject="null" body="DCB_ASSOCIATION:ZC9EUMCIG51H0I1PTF7RMSU8I5IMLP4HR" toa="null" sc_toa="null" service_center="null" read="1" status="-1" locked="0" date_sent="0" sub_id="-1" readable_date="19 Nis 2022 01:50:34" contact_name="(Unknown)" />
  <sms protocol="0" address="7529" date="1650322234000" type="2" subject="null" body="DCB_ASSOCIATION:ZC9EUMCIG51H0I1PTF7RMSU8I5IMLP4HR" toa="null" sc_toa="null" service_center="null" read="1" status="-1" locked="0" date_sent="0" sub_id="-1" readable_date="19 Nis 2022 01:50:34" contact_name="(Unknown)" />
  <sms protocol="0" address="+905551749100" date="1650340580000" type="2" subject="null" body="Şimdi güvendeyim. Endişelenme." toa="null" sc_toa="null" service_center="null" read="1" status="-1" locked="0" date_sent="0" sub_id="-1" readable_date="19 Nis 2022 06:56:20" contact_name="Kadir" />
  <sms protocol="0" address="+905343302404" date="1650344416000" type="1" subject="null" body="Bugundemi yoksun" toa="null" sc_toa="null" service_center="null" read="1" status="-1" locked="0" date_sent="0" sub_id="-1" readable_date="19 Nis 2022 08:00:16" contact_name="(Unknown)" />
  <sms protocol="0" address="+905343302404" date="1650344416000" type="1" subject="null" body="Bugundemi yoksun" toa="null" sc_toa="null" service_center="null" read="1" status="-1" locked="0" date_sent="0" sub_id="-1" readable_date="19 Nis 2022 08:00:16" contact_name="(Unknown)" />
  <sms protocol="0" address="+905343302404" date="1650344471000" type="2" subject="null" body="Evet abi rahatsizim" toa="null" sc_toa="null" service_center="null" read="1" status="-1" locked="0" date_sent="0" sub_id="-1" readable_date="19 Nis 2022 08:01:11" contact_name="(Unknown)" />
  <sms protocol="0" address="+905343302404" date="1650344471000" type="2" subject="null" body="Evet abi rahatsizim" toa="null" sc_toa="null" service_center="null" read="1" status="-1" locked="0" date_sent="0" sub_id="-1" readable_date="19 Nis 2022 08:01:11" contact_name="(Unknown)" />
  <sms protocol="0" address="Whatsapp" date="1650357842000" type="1" subject="null" body="&lt;#&gt; Size ait bir hesap (WhatsApp) yeni bir cihazda kaydediliyor&#13;&#10;&#13;&#10;Bu kodu kimseye vermeyin&#13;&#10;&#13;&#10;WhatsApp kodunuz: 843-319&#13;&#10;&#13;&#10;4sgLq1p5sV6 B273" toa="null" sc_toa="null" service_center="null" read="0" status="-1" locked="0" date_sent="0" sub_id="-1" readable_date="19 Nis 2022 11:44:02" contact_name="(Unknown)" />
  <sms protocol="0" address="Whatsapp" date="1650358142000" type="1" subject="null" body="&lt;#&gt; WhatsApp kod: 599-120&#13;&#10;&#13;&#10;Dogrula: v.whatsapp.com/599120&#13;&#10;&#13;&#10;Kodu paylasmayin&#13;&#10;4sgLq1p5sV6 B273" toa="null" sc_toa="null" service_center="null" read="0" status="-1" locked="0" date_sent="0" sub_id="-1" readable_date="19 Nis 2022 11:49:02" contact_name="(Unknown)" />
  <sms protocol="0" address="TURKTELEKOM" date="1650359823000" type="1" subject="null" body="Degerli musterimiz Google Play Storedan gerceklestirdiginiz mobil odeme islemi sonrasinda hattiniz Mobil Odeme kullanimina acilmistir. Turk Telekom Mobil Odeme ayricaligi ile keyifli alisverisler dileriz. B001" toa="null" sc_toa="null" service_center="null" read="1" status="-1" locked="0" date_sent="0" sub_id="-1" readable_date="19 Nis 2022 12:17:03" contact_name="(Unknown)" />
  <sms protocol="0" address="9230" date="1650359824000" type="1" subject="null" body="Degerli Musterimiz, Turk Telekom Mobil Odeme isleminiz basari ile mobil faturaniza yansitilmistir. Keyifli alisverisler dileriz. B001" toa="null" sc_toa="null" service_center="null" read="1" status="-1" locked="0" date_sent="0" sub_id="-1" readable_date="19 Nis 2022 12:17:04" contact_name="(Unknown)" />
  <sms protocol="0" address="7529" date="1650359838000" type="1" subject="null" body="Google Play'den satin aldiginiz urune karsilik 89.99 TL'lik alisveris tutari hattinizdan tahsil edilmistir. Destek icin: https://support.google.com/googleplay?hl=tr http://turktelekom.ly/ttohaskullanicisozlesmesi B001" toa="null" sc_toa="null" service_center="null" read="1" status="-1" locked="0" date_sent="0" sub_id="-1" readable_date="19 Nis 2022 12:17:18" contact_name="(Unknown)" />
  <sms protocol="0" address="KADES" date="1650387261313" type="1" subject="null" body="KADES Uygulamasi Dogrulama Kodunuz : JVR6ZF B002" toa="null" sc_toa="null" service_center="+905329065700" read="1" status="-1" locked="0" date_sent="1650387261000" sub_id="1" readable_date="19 Nis 2022 19:54:21" contact_name="(Unknown)" />
  <sms protocol="0" address="KADES" date="1650388088744" type="1" subject="null" body="KADES Uygulamasi Dogrulama Kodunuz : EEREFF B002" toa="null" sc_toa="null" service_center="+905329043410" read="1" status="-1" locked="0" date_sent="1650388088000" sub_id="1" readable_date="19 Nis 2022 20:08:08" contact_name="(Unknown)" />
  <sms protocol="0" address="KADES" date="1650388390952" type="1" subject="null" body="KADES Uygulamasi Dogrulama Kodunuz : 6AEKER B002" toa="null" sc_toa="null" service_center="+905329043410" read="1" status="-1" locked="0" date_sent="1650388390000" sub_id="1" readable_date="19 Nis 2022 20:13:10" contact_name="(Unknown)" />
  <sms protocol="0" address="EVKUR" date="1650445078694" type="1" subject="null" body="SAYIN GAMZE YILDIZ Geciken Borcunuzu Lütfen Ödeyiniz.Bilgi icin 02124734646 Mersis:382019471100366 B030" toa="null" sc_toa="null" service_center="+903124253896" read="1" status="-1" locked="0" date_sent="1650445075000" sub_id="1" readable_date="20 Nis 2022 11:57:58" contact_name="(Unknown)" />
  <sms protocol="0" address="+905377045482" date="1650449292024" type="1" subject="null" body="Şimdi " toa="null" sc_toa="null" service_center="+905429800033" read="1" status="-1" locked="0" date_sent="1650449292000" sub_id="1" readable_date="20 Nis 2022 13:08:12" contact_name="(Unknown)" />
  <sms protocol="0" address="+905377045482" date="1650449330321" type="2" subject="null" body="Azima scti bise olmadi..." toa="null" sc_toa="null" service_center="null" read="1" status="-1" locked="0" date_sent="0" sub_id="1" readable_date="20 Nis 2022 13:08:50" contact_name="(Unknown)" />
  <sms protocol="0" address="+905377045482" date="1650449348374" type="1" subject="null" body="Nqptıki " toa="null" sc_toa="null" service_center="+905429800033" read="1" status="-1" locked="0" date_sent="1650449347000" sub_id="1" readable_date="20 Nis 2022 13:09:08" contact_name="(Unknown)" />
  <sms protocol="0" address="+905377045482" date="1650449352334" type="1" subject="null" body="Bişe yapmamış " toa="null" sc_toa="null" service_center="+905429800033" read="1" status="-1" locked="0" date_sent="1650449352000" sub_id="1" readable_date="20 Nis 2022 13:09:12" contact_name="(Unknown)" />
  <sms protocol="0" address="+905377045482" date="1650449366191" type="1" subject="null" body="Tülay öğle " toa="null" sc_toa="null" service_center="+905429800033" read="1" status="-1" locked="0" date_sent="1650449365000" sub_id="1" readable_date="20 Nis 2022 13:09:26" contact_name="(Unknown)" />
  <sms protocol="0" address="+905377045482" date="1650449367546" type="1" subject="null" body="Dedi" toa="null" sc_toa="null" service_center="+905429800033" read="1" status="-1" locked="0" date_sent="1650449367000" sub_id="1" readable_date="20 Nis 2022 13:09:27" contact_name="(Unknown)" />
  <sms protocol="0" address="+905377045482" date="1650449371869" type="2" subject="null" body="Dovdu asagidaki eve goturup" toa="null" sc_toa="null" service_center="null" read="1" status="-1" locked="0" date_sent="0" sub_id="1" readable_date="20 Nis 2022 13:09:31" contact_name="(Unknown)" />
  <sms protocol="0" address="+905377045482" date="1650449383574" type="2" subject="null" body="3 kez bicak cekti" toa="null" sc_toa="null" service_center="null" read="1" status="-1" locked="0" date_sent="0" sub_id="1" readable_date="20 Nis 2022 13:09:43" contact_name="(Unknown)" />
  <sms protocol="0" address="+905377045482" date="1650449399497" type="1" subject="null" body="Vallahamı" toa="null" sc_toa="null" service_center="+905429800033" read="1" status="-1" locked="0" date_sent="1650449399000" sub_id="1" readable_date="20 Nis 2022 13:09:59" contact_name="(Unknown)" />
  <sms protocol="0" address="+905377045482" date="1650449409522" type="2" subject="null" body="Burnum incilmis Hala agriyo yuzum sis daha nolcak" toa="null" sc_toa="null" service_center="null" read="1" status="-1" locked="0" date_sent="0" sub_id="1" readable_date="20 Nis 2022 13:10:09" contact_name="(Unknown)" />
  <sms protocol="0" address="+905377045482" date="1650449435914" type="2" subject="null" body="Yuzume yuzume vurdu" toa="null" sc_toa="null" service_center="null" read="1" status="-1" locked="0" date_sent="0" sub_id="1" readable_date="20 Nis 2022 13:10:35" contact_name="(Unknown)" />
  <sms protocol="0" address="+905377045482" date="1650449461557" type="1" subject="null" body="Nasıl" toa="null" sc_toa="null" service_center="+905429800033" read="1" status="-1" locked="0" date_sent="1650449461000" sub_id="1" readable_date="20 Nis 2022 13:11:01" contact_name="(Unknown)" />
  <sms protocol="0" address="+905377045482" date="1650449498818" type="1" subject="null" body="Yakalqndın" toa="null" sc_toa="null" service_center="+905429800033" read="1" status="-1" locked="0" date_sent="1650449498000" sub_id="1" readable_date="20 Nis 2022 13:11:38" contact_name="(Unknown)" />
  <sms protocol="0" address="+905377045482" date="1650449508737" type="2" subject="null" body="Dukkandaym msj atma nolur bidaha gorurse bu sefer km kimi oldururse" toa="null" sc_toa="null" service_center="null" read="1" status="-1" locked="0" date_sent="0" sub_id="1" readable_date="20 Nis 2022 13:11:48" contact_name="(Unknown)" />
  <sms protocol="0" address="+905377045482" date="1650449529533" type="1" subject="null" body="Yaben görüşmek istiyorum" toa="null" sc_toa="null" service_center="+905429800033" read="1" status="-1" locked="0" date_sent="1650449528000" sub_id="1" readable_date="20 Nis 2022 13:12:09" contact_name="(Unknown)" />
  <sms protocol="0" address="+905377045482" date="1650449530399" type="2" subject="null" body="Sadece otomotik msj varya onu gormus" toa="null" sc_toa="null" service_center="null" read="1" status="-1" locked="0" date_sent="0" sub_id="1" readable_date="20 Nis 2022 13:12:10" contact_name="(Unknown)" />
  <sms protocol="0" address="+905377045482" date="1650449538023" type="1" subject="null" body="Seninle" toa="null" sc_toa="null" service_center="+905429800033" read="1" status="-1" locked="0" date_sent="1650449538000" sub_id="1" readable_date="20 Nis 2022 13:12:18" contact_name="(Unknown)" />
  <sms protocol="0" address="+905377045482" date="1650449545892" type="2" subject="null" body="Endiselenme falan yaziyoya" toa="null" sc_toa="null" service_center="null" read="1" status="-1" locked="0" date_sent="0" sub_id="1" readable_date="20 Nis 2022 13:12:25" contact_name="(Unknown)" />
  <sms protocol="0" address="+905377045482" date="1650449554496" type="1" subject="null" body="Hmm" toa="null" sc_toa="null" service_center="+905429800033" read="1" status="-1" locked="0" date_sent="1650449554000" sub_id="1" readable_date="20 Nis 2022 13:12:34" contact_name="(Unknown)" />
  <sms protocol="0" address="+905377045482" date="1650449562720" type="1" subject="null" body="Biraz bekkeyelim" toa="null" sc_toa="null" service_center="+905429800033" read="1" status="-1" locked="0" date_sent="1650449563000" sub_id="1" readable_date="20 Nis 2022 13:12:42" contact_name="(Unknown)" />
  <sms protocol="0" address="+905377045482" date="1650449566506" type="1" subject="null" body="Sonra " toa="null" sc_toa="null" service_center="+905429800033" read="1" status="-1" locked="0" date_sent="1650449566000" sub_id="1" readable_date="20 Nis 2022 13:12:46" contact_name="(Unknown)" />
  <sms protocol="0" address="+905377045482" date="1650449567088" type="2" subject="null" body="Hami lutfen msj atma" toa="null" sc_toa="null" service_center="null" read="1" status="-1" locked="0" date_sent="0" sub_id="1" readable_date="20 Nis 2022 13:12:47" contact_name="(Unknown)" />
  <sms protocol="0" address="+905377045482" date="1650449582511" type="1" subject="null" body="Ya bak" toa="null" sc_toa="null" service_center="+905429800033" read="1" status="-1" locked="0" date_sent="1650449582000" sub_id="1" readable_date="20 Nis 2022 13:13:02" contact_name="(Unknown)" />
  <sms protocol="0" address="+905377045482" date="1650449588249" type="1" subject="null" body="Bşrqz bekleyelim " toa="null" sc_toa="null" service_center="+905429800033" read="1" status="-1" locked="0" date_sent="1650449588000" sub_id="1" readable_date="20 Nis 2022 13:13:08" contact_name="(Unknown)" />
  <sms protocol="0" address="+905377045482" date="1650449599286" type="2" subject="null" body="Bu isin sonu kotuye gidiyo" toa="null" sc_toa="null" service_center="null" read="1" status="-1" locked="0" date_sent="0" sub_id="1" readable_date="20 Nis 2022 13:13:19" contact_name="(Unknown)" />
  <sms protocol="0" address="+905377045482" date="1650449602217" type="1" subject="null" body="Sonra görrüşelim" toa="null" sc_toa="null" service_center="+905429800033" read="1" status="-1" locked="0" date_sent="1650449602000" sub_id="1" readable_date="20 Nis 2022 13:13:22" contact_name="(Unknown)" />
  <sms protocol="0" address="+905377045482" date="1650449602330" type="2" subject="null" body="Ee" toa="null" sc_toa="null" service_center="null" read="1" status="-1" locked="0" date_sent="0" sub_id="1" readable_date="20 Nis 2022 13:13:22" contact_name="(Unknown)" />
  <sms protocol="0" address="+905377045482" date="1650449626347" type="2" subject="null" body="Nie goruscezki hami" toa="null" sc_toa="null" service_center="null" read="1" status="-1" locked="0" date_sent="0" sub_id="1" readable_date="20 Nis 2022 13:13:46" contact_name="(Unknown)" />
  <sms protocol="0" address="+905377045482" date="1650449627668" type="1" subject="null" body="Ama bu olay olmasaydı" toa="null" sc_toa="null" service_center="+905429800033" read="1" status="-1" locked="0" date_sent="1650449628000" sub_id="1" readable_date="20 Nis 2022 13:13:47" contact_name="(Unknown)" />
  <sms protocol="0" address="+905377045482" date="1650449652260" type="1" subject="null" body="Ben tülayı " toa="null" sc_toa="null" service_center="+905429800033" read="1" status="-1" locked="0" date_sent="1650449651000" sub_id="1" readable_date="20 Nis 2022 13:14:12" contact_name="(Unknown)" />
  <sms protocol="0" address="+905377045482" date="1650449658032" type="1" subject="null" body="Sevmşyorum " toa="null" sc_toa="null" service_center="+905429800033" read="1" status="-1" locked="0" date_sent="1650449658000" sub_id="1" readable_date="20 Nis 2022 13:14:18" contact_name="(Unknown)" />
  <sms protocol="0" address="+905377045482" date="1650449666434" type="1" subject="null" body="Kadirde seni " toa="null" sc_toa="null" service_center="+905429800033" read="1" status="-1" locked="0" date_sent="1650449666000" sub_id="1" readable_date="20 Nis 2022 13:14:26" contact_name="(Unknown)" />
  <sms protocol="0" address="+905377045482" date="1650449671836" type="2" subject="null" body="Ben dun orduyu terkediyordum" toa="null" sc_toa="null" service_center="null" read="1" status="-1" locked="0" date_sent="0" sub_id="1" readable_date="20 Nis 2022 13:14:31" contact_name="(Unknown)" />
  <sms protocol="0" address="+905377045482" date="1650449673288" type="1" subject="null" body="Sevmiyo" toa="null" sc_toa="null" service_center="+905429800033" read="1" status="-1" locked="0" date_sent="1650449673000" sub_id="1" readable_date="20 Nis 2022 13:14:33" contact_name="(Unknown)" />
  <sms protocol="0" address="+905377045482" date="1650449680284" type="2" subject="null" body="Biliyrm" toa="null" sc_toa="null" service_center="null" read="1" status="-1" locked="0" date_sent="0" sub_id="1" readable_date="20 Nis 2022 13:14:40" contact_name="(Unknown)" />
  <sms protocol="0" address="+905377045482" date="1650449683346" type="2" subject="null" body="Ama" toa="null" sc_toa="null" service_center="null" read="1" status="-1" locked="0" date_sent="0" sub_id="1" readable_date="20 Nis 2022 13:14:43" contact_name="(Unknown)" />
  <sms protocol="0" address="+905377045482" date="1650449686364" type="2" subject="null" body="Cocuklar" toa="null" sc_toa="null" service_center="null" read="1" status="-1" locked="0" date_sent="0" sub_id="1" readable_date="20 Nis 2022 13:14:46" contact_name="(Unknown)" />
  <sms protocol="0" address="+905377045482" date="1650449705371" type="1" subject="null" body="Sen" toa="null" sc_toa="null" service_center="+905429800033" read="1" status="-1" locked="0" date_sent="1650449705000" sub_id="1" readable_date="20 Nis 2022 13:15:05" contact_name="(Unknown)" />
  <sms protocol="0" address="+905377045482" date="1650449712022" type="1" subject="null" body="De sevmiyorsun" toa="null" sc_toa="null" service_center="+905429800033" read="1" status="-1" locked="0" date_sent="1650449712000" sub_id="1" readable_date="20 Nis 2022 13:15:12" contact_name="(Unknown)" />
  <sms protocol="0" address="+905377045482" date="1650449719961" type="1" subject="null" body="Kadiri" toa="null" sc_toa="null" service_center="+905429800033" read="1" status="-1" locked="0" date_sent="1650449720000" sub_id="1" readable_date="20 Nis 2022 13:15:19" contact_name="(Unknown)" />
  <sms protocol="0" address="+905377045482" date="1650449721017" type="2" subject="null" body="Ne sucu var cocuklarin" toa="null" sc_toa="null" service_center="null" read="1" status="-1" locked="0" date_sent="0" sub_id="1" readable_date="20 Nis 2022 13:15:21" contact_name="(Unknown)" />
  <sms protocol="0" address="+905377045482" date="1650449730358" type="2" subject="null" body="Hami lutfen" toa="null" sc_toa="null" service_center="null" read="1" status="-1" locked="0" date_sent="0" sub_id="1" readable_date="20 Nis 2022 13:15:30" contact_name="(Unknown)" />
  <sms protocol="0" address="+905377045482" date="1650449737199" type="2" subject="null" body="Msj atma" toa="null" sc_toa="null" service_center="null" read="1" status="-1" locked="0" date_sent="0" sub_id="1" readable_date="20 Nis 2022 13:15:37" contact_name="(Unknown)" />
  <sms protocol="0" address="+905377045482" date="1650449741762" type="2" subject="null" body="Yalvariyorm" toa="null" sc_toa="null" service_center="null" read="1" status="-1" locked="0" date_sent="0" sub_id="1" readable_date="20 Nis 2022 13:15:41" contact_name="(Unknown)" />
  <sms protocol="0" address="+905377045482" date="1650449777760" type="1" subject="null" body="Gamze 1 dk " toa="null" sc_toa="null" service_center="+905429800033" read="1" status="-1" locked="0" date_sent="1650449777000" sub_id="1" readable_date="20 Nis 2022 13:16:17" contact_name="(Unknown)" />
  <sms protocol="0" address="+905377045482" date="1650449782589" type="1" subject="null" body="Grşelim " toa="null" sc_toa="null" service_center="+905429800033" read="1" status="-1" locked="0" date_sent="1650449782000" sub_id="1" readable_date="20 Nis 2022 13:16:22" contact_name="(Unknown)" />
  <sms protocol="0" address="+905377045482" date="1650449833400" type="1" subject="null" body="Bak sende  sevmiyorsun kqdiri " toa="null" sc_toa="null" service_center="+905429800033" read="1" status="-1" locked="0" date_sent="1650449833000" sub_id="1" readable_date="20 Nis 2022 13:17:13" contact_name="(Unknown)" />
  <sms protocol="0" address="+905377045482" date="1650449862317" type="1" subject="null" body="Ayda bir kere görüşürüz hiç bişe olmaz" toa="null" sc_toa="null" service_center="+905429800033" read="1" status="-1" locked="0" date_sent="1650449861000" sub_id="1" readable_date="20 Nis 2022 13:17:42" contact_name="(Unknown)" />
  <sms protocol="0" address="7529" date="1650450530287" type="2" subject="null" body=" Jjh" toa="null" sc_toa="null" service_center="null" read="1" status="-1" locked="0" date_sent="0" sub_id="1" readable_date="20 Nis 2022 13:28:50" contact_name="(Unknown)" />
  <sms protocol="0" address="WATSONS" date="1650529809104" type="1" subject="null" body="Watsons'ta buyuk bayram firsatlari basladi! Wcard'a ozel %50'ye varan indirim. Alisveris icin: bit.ly/WTSK15 Cikis: WTS yaz 4946 gonder Mersis: 0212037036400019 B016" toa="null" sc_toa="null" service_center="+908503157001" read="1" status="-1" locked="0" date_sent="1650529806000" sub_id="1" readable_date="21 Nis 2022 11:30:09" contact_name="(Unknown)" />
  <sms protocol="0" address="Google" date="1650610903116" type="1" subject="null" body="Your Messenger verification code is G-027581 B356" toa="null" sc_toa="null" service_center="+908509383001" read="1" status="-1" locked="0" date_sent="1650610902000" sub_id="1" readable_date="22 Nis 2022 10:01:43" contact_name="(Unknown)" />
  <sms protocol="0" address="Google" date="1650612272759" type="1" subject="null" body="Your Messenger verification code is G-597502 B356" toa="null" sc_toa="null" service_center="+908509383001" read="1" status="-1" locked="0" date_sent="1650612273000" sub_id="1" readable_date="22 Nis 2022 10:24:32" contact_name="(Unknown)" />
  <sms protocol="0" address="Google" date="1650612805015" type="1" subject="null" body="Your Messenger verification code is G-597502 B356" toa="null" sc_toa="null" service_center="+908509383001" read="1" status="-1" locked="0" date_sent="1650612805000" sub_id="1" readable_date="22 Nis 2022 10:33:25" contact_name="(Unknown)" />
  <sms protocol="0" address="FUZUL EV" date="1650616204918" type="1" subject="null" body="Fuzul'den Kaçırılmayacak Fırsat! Ayda Sadece 1.250 TL'den başlayan Taksitlerle Ev Sahibi Olma Fırsatı Fuzul İle Mümkün! Faizsiz, peşinatsız, kredisiz ayda sadece 1.250 TL'den başlayan taksitlerle hayallerindeki eve kavuşma fırsatı şimdi Fuzul'de! Kampanya detayları için hemen 444 63 13'ü arayın ya da fuzulev.com'u ziyaret edin! Üstelik size özel organizasyon ücretinde %20 indirim fırsatı ile! / https://bit.ly/38YsDL4 SMS iptal FUZUL IPTAL yazıp 4946'ya gönderebilirsiniz 0388073044200010 B002" toa="null" sc_toa="null" service_center="+905329043410" read="1" status="-1" locked="0" date_sent="1650616202000" sub_id="1" readable_date="22 Nis 2022 11:30:04" contact_name="(Unknown)" />
  <sms protocol="0" address="PAPARA" date="1650627180239" type="1" subject="null" body="Papara giris sifreniz 937378. KIMSEYLE PAYLASMAYINIZ. B002" toa="null" sc_toa="null" service_center="+905329065500" read="1" status="-1" locked="0" date_sent="1650627179000" sub_id="1" readable_date="22 Nis 2022 14:33:00" contact_name="(Unknown)" />
  <sms protocol="0" address="Papara" date="1650627279883" type="1" subject="null" body="Papara giris sifreniz 571336. KIMSEYLE PAYLASMAYINIZ. B040" toa="null" sc_toa="null" service_center="+908505400003" read="1" status="-1" locked="0" date_sent="1650627280000" sub_id="1" readable_date="22 Nis 2022 14:34:39" contact_name="(Unknown)" />
  <sms protocol="0" address="PAPARA" date="1650627341349" type="1" subject="null" body="Papara giris sifreniz 578948. KIMSEYLE PAYLASMAYINIZ. B002" toa="null" sc_toa="null" service_center="+905329043410" read="1" status="-1" locked="0" date_sent="1650627340000" sub_id="1" readable_date="22 Nis 2022 14:35:41" contact_name="(Unknown)" />
  <sms protocol="0" address="+905414311675" date="1650696078286" type="1" subject="null" body="Abla ara beni birseymi var " toa="null" sc_toa="null" service_center="+905429800033" read="1" status="-1" locked="0" date_sent="1650696078000" sub_id="1" readable_date="23 Nis 2022 09:41:18" contact_name="Aydin" />
  <sms protocol="0" address="DeFacto" date="1650722907684" type="1" subject="null" body="Mobil Uygulamada KARGO BEDAVA! Tüm Ürünlerde Bayram Fırsatını Kaçırma! https://dfurl.com/2VwZEx SMS ret için DF RET yaz 7889'a gönder MK:0650003471600013 B016" toa="null" sc_toa="null" service_center="+908503157003" read="1" status="-1" locked="0" date_sent="1650722904000" sub_id="1" readable_date="23 Nis 2022 17:08:27" contact_name="(Unknown)" />
  <sms protocol="0" address="+905428797967" date="1650724797433" type="1" subject="null" body="BUGUNE OZEL UYELIGINIZE GIRIS YAPIP BENI ARA KISMINDAN ARAMA TALEP EDIN %100 - 1.000 TL CEVRIMSIZ BONUS KAZANIN, HER AY 2 YATIRIMA %50 BONUS : www.onwin390.com" toa="null" sc_toa="null" service_center="+908504140500" read="1" status="-1" locked="0" date_sent="1650724797000" sub_id="1" readable_date="23 Nis 2022 17:39:57" contact_name="(Unknown)" />
  <sms protocol="0" address="FLO" date="1650793940210" type="1" subject="null" body="KARGO BEDAVA FIRSATI! Tüm Ürünlerde Geçerli Fırsatı Kaçırma, Hemen Alışverişe Başla: https://flo.tm/kr2 Son Gün: 24 Nisan SMS RET:FLO-&gt;3525 MN:0388023942900019 B018" toa="null" sc_toa="null" service_center="+908509690210" read="1" status="-1" locked="0" date_sent="1650793938000" sub_id="1" readable_date="24 Nis 2022 12:52:20" contact_name="(Unknown)" />
  <sms protocol="0" address="+905488405956" date="1650804432888" type="1" subject="null" body="BUGUNE OZEL UYELIGINIZE GIRIS YAPIP BENI ARA KISMINDAN ARAMA TALEP EDIN %100 - 1.000 TL CEVRIMSIZ BONUS KAZANIN, HER AY 2 YATIRIMA %50 BONUS : www.onwin390.com" toa="null" sc_toa="null" service_center="+908504140500" read="1" status="-1" locked="0" date_sent="1650804432000" sub_id="1" readable_date="24 Nis 2022 15:47:12" contact_name="(Unknown)" />
  <sms protocol="0" address="+905414311675" date="1650921810620" type="2" subject="null" body="Şimdi konuşamam." toa="null" sc_toa="null" service_center="null" read="1" status="-1" locked="0" date_sent="0" sub_id="1" readable_date="26 Nis 2022 00:23:30" contact_name="Aydin" />
  <sms protocol="0" address="WATSONS" date="1650969935546" type="1" subject="null" body="WCard'a watsons.com.tr ve mobil uygulamadan 150 TL ve ustu alisverisine 120 TL hediye! Alisveris icin: bit.ly/WTS3Z11 Cks: WTS yaz 4946 gndr M: 0212037036400019 B016" toa="null" sc_toa="null" service_center="+908503157001" read="1" status="-1" locked="0" date_sent="1650969932000" sub_id="1" readable_date="26 Nis 2022 13:45:35" contact_name="(Unknown)" />
  <sms protocol="0" address="+905428797967" date="1650980084421" type="1" subject="null" body="BUGUNE OZEL HAVALE - EFT YATIRIMA %100 - 300 TL YATIRIM BONUSU, %25 SLOT YATIRIM BONUSU, %30 CASINO KAYIP BONUSU, 100.000 TL TEK SEFERDE CEKIM: www.onwin391.com" toa="null" sc_toa="null" service_center="+908504140500" read="1" status="-1" locked="0" date_sent="1650980083000" sub_id="1" readable_date="26 Nis 2022 16:34:44" contact_name="(Unknown)" />
  <sms protocol="0" address="FLO" date="1650985887255" type="1" subject="null" body="Ailenin Tüm Üyelerine Bayram Ettirecek Fiyatlar FLO Mağazaları ve flo.com.tr'de! Üstelik FLO Cüzdan'ın ayrıcalıklı dünyası ile flo.com.tr'de yapacağınız alışverişlerde %1 FLO Para kazanabilirsiniz. Hemen FLO Cüzdan'ını aktive et, alışverişe başla: https://flo.tm/brm Son Gün:5 Mayıs SMS RET:FLO-&gt;3525 MN:0388023942900019 B018" toa="null" sc_toa="null" service_center="+908509690210" read="1" status="-1" locked="0" date_sent="1650981929000" sub_id="1" readable_date="26 Nis 2022 18:11:27" contact_name="(Unknown)" />
  <sms protocol="0" address="+905488279173" date="1651075711377" type="1" subject="null" body="BUGUNE OZEL UYELIGINIZE GIRIS YAPIP BENI ARA KISMINDAN ARAMA TALEP EDIN %100 - 1.000 TL CEVRIMSIZ BONUS KAZANIN, HER AY 2 YATIRIMA %50 BONUS : www.onwin393.com" toa="null" sc_toa="null" service_center="+908504140500" read="1" status="-1" locked="0" date_sent="1651075710000" sub_id="1" readable_date="27 Nis 2022 19:08:31" contact_name="(Unknown)" />
  <sms protocol="0" address="9230" date="1651101056047" type="1" subject="null" body="Degerli Musterimiz, Turk Telekom Mobil Odeme isleminiz basari ile mobil faturaniza yansitilmistir. Keyifli alisverisler dileriz. B001" toa="null" sc_toa="null" service_center="+905598008000" read="1" status="-1" locked="0" date_sent="1651101055000" sub_id="1" readable_date="28 Nis 2022 02:10:56" contact_name="(Unknown)" />
  <sms protocol="0" address="7529" date="1651101068202" type="1" subject="null" body="Google Play'de baslattiginiz abonelik ucreti olan 91.99 TL hattinizdan tahsil edilmistir. Aboneliginizi Google Play'den iptal edebilirsiniz. Destek icin: https://support.google.com/googleplay?hl=tr http://turktelekom.ly/ttohaskullanicisozlesmesi B001" toa="null" sc_toa="null" service_center="+905598008000" read="1" status="-1" locked="0" date_sent="1651101055000" sub_id="1" readable_date="28 Nis 2022 02:11:08" contact_name="(Unknown)" />
  <sms protocol="0" address="TURKTELEKOM" date="1651102701189" type="1" subject="null" body="Mobil hattinizin guncel fatura tutari vergiler dahil, FATURA UST SINIRI limitiniz olan 100  TLye ulasmistir. Toplam fatura bedeli uzerinden yapilan indirimler, yurt disi DK ve SMS kullanimlarindan henuz bilgisi ulasmamis olanlar dahil degildir. Son 6 saat harictir. Bu bilgilendirmeleri almak istemiyorsaniz IPTAL FUS yazip 5555e gonderebilirsiniz. Bilgi: turktelekom.com.tr B001" toa="null" sc_toa="null" service_center="+905598008000" read="1" status="-1" locked="0" date_sent="1651102700000" sub_id="1" readable_date="28 Nis 2022 02:38:21" contact_name="(Unknown)" />
  <sms protocol="0" address="+908505519910" date="1651133190954" type="2" subject="null" body="(wvgKQbjxPHXL) Google SIM doğrulaması https://goo.gl/LHCS9W" toa="null" sc_toa="null" service_center="null" read="1" status="-1" locked="0" date_sent="0" sub_id="2" readable_date="28 Nis 2022 11:06:30" contact_name="(Unknown)" />
  <sms protocol="0" address="+67976341041" date="1651141615625" type="1" subject="null" body="Man.Utd v Chelsea bugun youwin de! 05111990 www.hepsibahis346.com da ilk transferinle 1200TLye kadar %100 kazan, Premier League bahislerini kacirma!" toa="null" sc_toa="null" service_center="+6797000009" read="1" status="-1" locked="0" date_sent="1651141612000" sub_id="2" readable_date="28 Nis 2022 13:26:55" contact_name="(Unknown)" />
  <sms protocol="0" address="AKSA D.GAZ" date="1651144585572" type="1" subject="null" body="Değerli Abonemiz (3115678) son ödeme tarihi geçmiş 831,73 TL borcunuz bulunmaktadır.Son ödeme tarihinden itibaren ödenmeyen borçlarda günlük gecikme faizi ve 15 gün içinde ödenmemesi durumda doğal gaz kesintisi uygulanmaktadır. Güncel borcunuzu web sitemizden ve e-devlet üzerinden takip edebilirsiniz. B016" toa="null" sc_toa="null" service_center="+908503157001" read="1" status="-1" locked="0" date_sent="1651144580000" sub_id="2" readable_date="28 Nis 2022 14:16:25" contact_name="(Unknown)" />
  <sms protocol="0" address="BIREVIM" date="1651173082458" type="1" subject="null" body="Tasarruf Finansının Mimarı BİREVİM, şimdi Bankacılık Düzenleme ve Denetleme Kurumu (BDDK) tarafından lisanslı bir tasarruf finansman şirketi! &#10;Tasarruf finansıyla 2023 yılı sonunda, 3 milyon aileyi ev ve araç hayallerine kavuşturmaya tüm hızıyla devam ediyoruz! Sizi de hayallerinizi gerçekleştirmeniz için BİREVİM’e bekliyoruz.&#10;Tasarruf artacak, Türkiye kazanacak!&#10;Detaylı bilgi almak için bize 444 23 53‘ten ulaşabilirsiniz.&#10;SMS iptal için BIREVIM yazıp 4609'a gönderebilirsiniz. MERSIS:0177036646000011 B001" toa="null" sc_toa="null" service_center="+905598008000" read="1" status="-1" locked="0" date_sent="1651173078000" sub_id="2" readable_date="28 Nis 2022 22:11:22" contact_name="(Unknown)" />
  <sms protocol="0" address="PTTCELL" date="1651214056433" type="1" subject="null" body="Degerli musterimiz, odeme tarihi gecen 132,00 TL tutarindaki faturaniz sebebiyle mobil hattiniz aramaya kapanmistir. Odemenizi online islemler ve mobil uygulamamiz uzerinden, bayi ve ofislerimizden, internet bankaciligini kullanarak veya 9333 u tuslayarak guvenle yapabilirsiniz. https://www.turktelekom.com.tr/m/mobil/faturalar Odeme yapildiysa bu mesaji dikkate almayiniz. B001" toa="null" sc_toa="null" service_center="+905598008000" read="1" status="-1" locked="0" date_sent="1651214053000" sub_id="2" readable_date="29 Nis 2022 09:34:16" contact_name="(Unknown)" />
  <sms protocol="0" address="FUZUL EV" date="1651219313215" type="1" subject="null" body="Değerli müşterilerimiz, Bildiğiniz üzere; Sektörümüzle ilgili 12 Mart 2021'de resmi olarak  BDDK süreci başlamıştı. Bugün açıklanan BDDK kararı ile FuzulEv artık intibak sürecini tamamlayarak lisansını aldı, FuzulEv artık Devlet onaylı. Artık 6361 Sayılı Finansal Kiralama, Faktoring ve Finansman Şirketleri Kanunları çerçevesinde daha da şeffaf, kurumsal bir yapı ile hızla büyüyeceğimiz bir döneme giriyoruz. Ülkemiz adına sevindirici bu gelişmeden siz değerli müşterilerimizi de haberdar etmek istedik. Şimdiden hayırlı bayramlar. https://bit.ly/3vtFGxa SMS iptal FUZUL IPTAL yazıp 4946'ya gönderebilirsiniz 0388073044200010 B002" toa="null" sc_toa="null" service_center="+905329065500" read="1" status="-1" locked="0" date_sent="1651219298000" sub_id="1" readable_date="29 Nis 2022 11:01:53" contact_name="(Unknown)" />
  <sms protocol="0" address="UNILEVER" date="1651226514656" type="1" subject="null" body="MAGNUM HAZZININ BU YILKİ HEDİYESİ MASERATİ! Magnum çubuklarındaki şifreyi hemen gir, Maserati Ghibli GT kazanma şansını yakala! Detaylı bilgi için: https://bit.ly/36YuGhL SMS almak istemiyorsan UNILEVER IPTAL yazıp 4946'ya gönderebilirsin. Mersis 0913002605100018 B016" toa="null" sc_toa="null" service_center="+908503157003" read="1" status="-1" locked="0" date_sent="1651226510000" sub_id="1" readable_date="29 Nis 2022 13:01:54" contact_name="(Unknown)" />
  <sms protocol="0" address="ON." date="1651236925434" type="1" subject="null" body="ON Banka karti ile yillik toplam 600 TL iade fırsatı ON'da! Aylik 1.000 TL uzeri internet alisverisine %5, toplamda yilda 600 TL iade icin https://burgan.com.tr/on/b/b9M5ZmNr adresinden ON'lu ol! Bilgi icin 0850 222 29 10 tanitim icerikli SMS almak istemiyorsan ON IPTAL yazip 3525'e ucretsiz gonderebilirsin.Mersis:0140003231000116 B016" toa="null" sc_toa="null" service_center="+908503157003" read="1" status="-1" locked="0" date_sent="1651236907000" sub_id="2" readable_date="29 Nis 2022 15:55:25" contact_name="(Unknown)" />
  <sms protocol="0" address="+905415508214" date="1651239486280" type="1" subject="null" body="Usta ben Osman ararmisin musayit sen" toa="null" sc_toa="null" service_center="+905429800033" read="1" status="-1" locked="0" date_sent="1651239485000" sub_id="2" readable_date="29 Nis 2022 16:38:06" contact_name="(Unknown)" />
  <sms protocol="0" address="+905428505342" date="1651244342752" type="1" subject="null" body="BUGUN PAYFIX YATIRIM YAPIN 300 TL %100 BONUS KAZANIN ! ILK YATIRIMA %100 1.000 TL CEVRIMSIZ BONUS, %30 LIMITSIZ KAYIP BONUSU, %25 SLOT YATIRIM: www.onwin395.com" toa="null" sc_toa="null" service_center="+908504140500" read="0" status="-1" locked="0" date_sent="1651244342000" sub_id="1" readable_date="29 Nis 2022 17:59:02" contact_name="(Unknown)" />
  <sms protocol="0" address="YEPAS" date="1651299146267" type="1" subject="null" body="Sayın ABDULKADİR YILDIZ,4002928581 hesabınıza ait 1 adet,toplam 520.50 TL tutarında vadesi geçmiş faturanız bulunmaktadır.Ödemenizi en kısa sürede yapmanızı rica ederiz.Ödeme yaptıysanız bu mesajı dikkate almayınız.444 55 23 B001" toa="null" sc_toa="null" service_center="+905598008000" read="1" status="-1" locked="0" date_sent="1651299142000" sub_id="2" readable_date="30 Nis 2022 09:12:26" contact_name="(Unknown)" />
  <sms protocol="4" address="ICISLERIBAK" date="1651309443825" type="1" subject="null" body="Trafikte dikkat dikkat ⚠️&#10;&#10;Sürücü de Yaya da kurala uymalı.&#10;&#10;2021 yılında trafik kazalarında ölenlerin %22’si yaya&#10;&#10;Yayaların karıştığı trafik kazalarının %58’i ise yaya kaynaklı&#10;&#10; Sağlığa Yürüyelim!&#10; B001" toa="null" sc_toa="null" service_center="+905590000373" read="1" status="-1" locked="0" date_sent="1651309441000" sub_id="1" readable_date="30 Nis 2022 12:04:03" contact_name="(Unknown)" />
  <sms protocol="0" address="+905415508214" date="1651318701826" type="1" subject="null" body="Beklim Usta" toa="null" sc_toa="null" service_center="+905429800033" read="1" status="-1" locked="0" date_sent="1651318699000" sub_id="2" readable_date="30 Nis 2022 14:38:21" contact_name="(Unknown)" />
  <sms protocol="0" address="+905312322913" date="1651322248058" type="2" subject="null" body="Geliyomusun" toa="null" sc_toa="null" service_center="null" read="1" status="-1" locked="0" date_sent="0" sub_id="1" readable_date="30 Nis 2022 15:37:28" contact_name="Mevlude" />
  <sms protocol="0" address="+905312322913" date="1651322252586" type="2" subject="null" body="Müşteri var" toa="null" sc_toa="null" service_center="null" read="1" status="-1" locked="0" date_sent="0" sub_id="1" readable_date="30 Nis 2022 15:37:32" contact_name="Mevlude" />
  <sms protocol="0" address="+905312322913" date="1651322395147" type="1" subject="null" body="Benm.musterm bayrama iptal etti randevusunu ondan gelmcm çocuk rahatsz onla ilglnyrm telefna bakamion" toa="null" sc_toa="null" service_center="+905329010000" read="1" status="-1" locked="0" date_sent="1651322394000" sub_id="1" readable_date="30 Nis 2022 15:39:55" contact_name="Mevlude" />
  <sms protocol="0" address="+905312322913" date="1651322470265" type="2" subject="null" body="Niye sadece kendi müşterilerinize geliyosunuz" toa="null" sc_toa="null" service_center="null" read="1" status="-1" locked="0" date_sent="0" sub_id="1" readable_date="30 Nis 2022 15:41:10" contact_name="Mevlude" />
  <sms protocol="0" address="+905312322913" date="1651322480963" type="2" subject="null" body="Anlamıyorum Bizim müşteriler adam degilmi" toa="null" sc_toa="null" service_center="null" read="1" status="-1" locked="0" date_sent="0" sub_id="1" readable_date="30 Nis 2022 15:41:20" contact_name="Mevlude" />
  <sms protocol="0" address="+905312322913" date="1651322602593" type="1" subject="null" body="Ne alaka gamze" toa="null" sc_toa="null" service_center="+905329010000" read="1" status="-1" locked="0" date_sent="1651322601000" sub_id="1" readable_date="30 Nis 2022 15:43:22" contact_name="Mevlude" />
  <sms protocol="0" address="+905312322913" date="1651322609702" type="1" subject="null" body="Erkenden hbermi veriyorsunz" toa="null" sc_toa="null" service_center="+905329010000" read="1" status="-1" locked="0" date_sent="1651322609000" sub_id="1" readable_date="30 Nis 2022 15:43:29" contact_name="Mevlude" />
  <sms protocol="0" address="+905312322913" date="1651322622363" type="1" subject="null" body="On kere dedmki randevuyu erkenden hber et" toa="null" sc_toa="null" service_center="+905329010000" read="1" status="-1" locked="0" date_sent="1651322621000" sub_id="1" readable_date="30 Nis 2022 15:43:42" contact_name="Mevlude" />
  <sms protocol="0" address="+905312322913" date="1651322628392" type="1" subject="null" body="Ona göre birini bulsun baktrmaya" toa="null" sc_toa="null" service_center="+905329010000" read="1" status="-1" locked="0" date_sent="1651322627000" sub_id="1" readable_date="30 Nis 2022 15:43:48" contact_name="Mevlude" />
  <sms protocol="0" address="+905312322913" date="1651322631847" type="2" subject="null" body="Erken haber verince de gelmiyonki" toa="null" sc_toa="null" service_center="null" read="1" status="-1" locked="0" date_sent="0" sub_id="1" readable_date="30 Nis 2022 15:43:51" contact_name="Mevlude" />
  <sms protocol="0" address="+905312322913" date="1651322642009" type="1" subject="null" body="Doğru düzgün ise.orda başlarsam zaten böyle olmaz" toa="null" sc_toa="null" service_center="+905329010000" read="1" status="-1" locked="0" date_sent="1651322641000" sub_id="1" readable_date="30 Nis 2022 15:44:02" contact_name="Mevlude" />
  <sms protocol="0" address="+905312322913" date="1651322663290" type="1" subject="null" body="Net bı maaş kararı veremyn sizsnz bnde ona göre bakıcı tutcm " toa="null" sc_toa="null" service_center="+905329010000" read="1" status="-1" locked="0" date_sent="1651322662000" sub_id="1" readable_date="30 Nis 2022 15:44:23" contact_name="Mevlude" />
  <sms protocol="0" address="+905312322913" date="1651322672215" type="1" subject="null" body="Hergun ele çocuk bak denmio" toa="null" sc_toa="null" service_center="+905329010000" read="1" status="-1" locked="0" date_sent="1651322671000" sub_id="1" readable_date="30 Nis 2022 15:44:32" contact_name="Mevlude" />
  <sms protocol="0" address="+905312322913" date="1651322705559" type="2" subject="null" body="Tmm kadirin işi bitsin arıcak seni" toa="null" sc_toa="null" service_center="null" read="1" status="-1" locked="0" date_sent="0" sub_id="1" readable_date="30 Nis 2022 15:45:05" contact_name="Mevlude" />
  <sms protocol="0" address="+905312322913" date="1651322728205" type="2" subject="null" body="Akşama müşteri var gelebilceksen " toa="null" sc_toa="null" service_center="null" read="1" status="-1" locked="0" date_sent="0" sub_id="1" readable_date="30 Nis 2022 15:45:28" contact_name="Mevlude" />
  <sms protocol="0" address="+905312322913" date="1651322733026" type="2" subject="null" body="Saat ver bize" toa="null" sc_toa="null" service_center="null" read="1" status="-1" locked="0" date_sent="0" sub_id="1" readable_date="30 Nis 2022 15:45:33" contact_name="Mevlude" />
  <sms protocol="0" address="+905312322913" date="1651322754220" type="2" subject="null" body="Makyaj falan yaptrcakmis" toa="null" sc_toa="null" service_center="null" read="1" status="-1" locked="0" date_sent="0" sub_id="1" readable_date="30 Nis 2022 15:45:54" contact_name="Mevlude" />
  <sms protocol="0" address="+905312322913" date="1651322829353" type="1" subject="null" body="Yok bugün gelemem" toa="null" sc_toa="null" service_center="+905329010000" read="1" status="-1" locked="0" date_sent="1651322828000" sub_id="1" readable_date="30 Nis 2022 15:47:09" contact_name="Mevlude" />
  <sms protocol="0" address="+905312322913" date="1651322830485" type="1" subject="null" body="Otrp knscz anlasrsak norml baslrm cnku verdgn tepki yersz" toa="null" sc_toa="null" service_center="+905329010000" read="1" status="-1" locked="0" date_sent="1651322828000" sub_id="1" readable_date="30 Nis 2022 15:47:10" contact_name="Mevlude" />
  <sms protocol="0" address="+905312322913" date="1651323011937" type="2" subject="null" body="Sen bilirsin" toa="null" sc_toa="null" service_center="null" read="1" status="-1" locked="0" date_sent="0" sub_id="1" readable_date="30 Nis 2022 15:50:11" contact_name="Mevlude" />
  <sms protocol="0" address="+905070643801" date="1651327802152" type="1" subject="null" body="Hos geldin bonusun youwinden!05111990 www.hepsibahis429.com da ilk transferinle 1200TLye kadar 100 bonus kazan!" toa="null" sc_toa="null" service_center="+905598008000" read="0" status="-1" locked="0" date_sent="1651327800000" sub_id="2" readable_date="30 Nis 2022 17:10:02" contact_name="(Unknown)" />
  <sms protocol="0" address="+905312322913" date="1651334737013" type="2" subject="null" body="Canan diyoki köye gidicem Tam onda ordayım bekletmesin rica ediyrm diyo " toa="null" sc_toa="null" service_center="null" read="1" status="-1" locked="0" date_sent="0" sub_id="1" readable_date="30 Nis 2022 19:05:37" contact_name="Mevlude" />
  <sms protocol="0" address="+905312322913" date="1651334748764" type="2" subject="null" body="Bende 9 30 da burda dedim" toa="null" sc_toa="null" service_center="null" read="1" status="-1" locked="0" date_sent="0" sub_id="1" readable_date="30 Nis 2022 19:05:48" contact_name="Mevlude" />
  <sms protocol="0" address="+905312322913" date="1651335497413" type="1" subject="null" body="Tamam " toa="null" sc_toa="null" service_center="+905329010000" read="1" status="-1" locked="0" date_sent="1651335496000" sub_id="1" readable_date="30 Nis 2022 19:18:17" contact_name="Mevlude" />
  <sms protocol="0" address="+905312322913" date="1651335498874" type="1" subject="null" body="Bekletme " toa="null" sc_toa="null" service_center="+905329010000" read="1" status="-1" locked="0" date_sent="1651335498000" sub_id="1" readable_date="30 Nis 2022 19:18:18" contact_name="Mevlude" />
  <sms protocol="0" address="+905312322913" date="1651335571476" type="1" subject="null" body="Siz dükkanı kaçta acionz" toa="null" sc_toa="null" service_center="+905329010000" read="1" status="-1" locked="0" date_sent="1651335570000" sub_id="1" readable_date="30 Nis 2022 19:19:31" contact_name="Mevlude" />
  <sms protocol="0" address="+905312322913" date="1651336109708" type="2" subject="null" body="Sekiz de acicaz " toa="null" sc_toa="null" service_center="null" read="1" status="-1" locked="0" date_sent="0" sub_id="1" readable_date="30 Nis 2022 19:28:29" contact_name="Mevlude" />
  <sms protocol="0" address="IN STREET" date="1651336702447" type="1" subject="null" body="IN STREET! SOKAK, TARZ, SNEAKER Türkiye'nin sneaker ve spor giyim zinciri IN STREET, ilk reklam filmi ile yayında, izlemek için tıkla: bit.ly/InStreetReklam Sokağın en sevilen markalarını keşfetmek için hemen alışverişe başla: bit.ly/3y3hFi4 SMS RET: FLO-&gt;3525 Mersis:0388023942900019 B018" toa="null" sc_toa="null" service_center="+908509690211" read="1" status="-1" locked="0" date_sent="1651336698000" sub_id="1" readable_date="30 Nis 2022 19:38:22" contact_name="(Unknown)" />
  <sms protocol="0" address="+905312322913" date="1651339240674" type="1" subject="null" body="Tamam yarn başka saat kaçta randevu var kadir birsuuru var diyordu saatleri yazarmsn bana işlemleriyle başka randevu alcam.ona gore" toa="null" sc_toa="null" service_center="+905329010000" read="1" status="-1" locked="0" date_sent="1651339239000" sub_id="1" readable_date="30 Nis 2022 20:20:40" contact_name="Mevlude" />
  <sms protocol="0" address="+905312322913" date="1651342351591" type="2" subject="null" body="Belirli bi saatleri yok sen gel yarın konusursunuz söylediğin agdayi falanda aldı kadir sen çağır müşterilerini " toa="null" sc_toa="null" service_center="null" read="1" status="-1" locked="0" date_sent="0" sub_id="1" readable_date="30 Nis 2022 21:12:31" contact_name="Mevlude" />
  <sms protocol="0" address="E-DEVLET" date="1651394750876" type="1" subject="null" body="Dogrulama kodunuz : 35127 . Bu mesaj e-Devlet Kapisi tarafindan 01/05/2022 11:45:48 itibariyle gonderilmistir. B016" toa="null" sc_toa="null" service_center="+908503157001" read="1" status="-1" locked="0" date_sent="1651394748000" sub_id="2" readable_date="1 May 2022 11:45:50" contact_name="(Unknown)" />
  <sms protocol="0" address="+905488793632" date="1651409959457" type="1" subject="null" body="Bugun Uyeliginize Giris Yapin ve Arama Talebi Olusturun Ilk Yatiriminiza %100 - 1.000 TL Bonus Kazanin, Sonraki 2 Yatirima %50 - 1.000 TL Bonus www.onwin395.com" toa="null" sc_toa="null" service_center="+908504140500" read="0" status="-1" locked="0" date_sent="1651409959000" sub_id="1" readable_date="1 May 2022 15:59:19" contact_name="(Unknown)" />
  <sms protocol="0" address="05350244092" date="1651438167653" type="2" subject="null" body="Benim berber" toa="null" sc_toa="null" service_center="null" read="1" status="-1" locked="0" date_sent="0" sub_id="1" readable_date="1 May 2022 23:49:27" contact_name="(Unknown)" />
  <sms protocol="0" address="05350244092" date="1651438170342" type="2" subject="null" body="Kadir" toa="null" sc_toa="null" service_center="null" read="1" status="-1" locked="0" date_sent="0" sub_id="1" readable_date="1 May 2022 23:49:30" contact_name="(Unknown)" />
  <sms protocol="0" address="MOBILFATURA" date="1651475265860" type="1" subject="null" body="Degerli musterimiz,22.04.2022 tarihinde 23:59'da kesilen fatura tutari 193,25 TL,son odeme tarihi 09.05.2022 dir.Bir sonraki faturaniz 22.05.2022 tarihinde kesilecektir.Faturalarinizi mobil hattinizdan 9333u UCRETSIZ arayarak veya Turktelekom.com.tr online islemlerden kredi kartinizla odeyebilirsiniz.Odeme yaptiysaniz bu mesaji dikkate almayiniz. B001" toa="null" sc_toa="null" service_center="+905598008000" read="1" status="-1" locked="0" date_sent="1651475264000" sub_id="1" readable_date="2 May 2022 10:07:45" contact_name="(Unknown)" />
  <sms protocol="0" address="+905322731995" date="1651481703428" type="1" subject="null" body="Niyazi başkan cevap verirsen trasa gelicem " toa="null" sc_toa="null" service_center="+905329010000" read="1" status="-1" locked="0" date_sent="1651481701000" sub_id="2" readable_date="2 May 2022 11:55:03" contact_name="Niyazi Baskan" />
  <sms protocol="0" address="YEDAS" date="1651483747128" type="1" subject="null" body="Değerli Müşterimiz, Ramazan bayramınızı kutlar, sağlıklı günler dileriz.Tüm işlemlerinizi wa.me/905301060186 linki üzerinden kolaylıkla sağlayabilirsiniz.Yeşilırmak Elektrik Dağıtım A.Ş. B016" toa="null" sc_toa="null" service_center="+908503157001" read="1" status="-1" locked="0" date_sent="1651483736000" sub_id="2" readable_date="2 May 2022 12:29:07" contact_name="(Unknown)" />
  <sms protocol="0" address="Pttcell" date="1651489731869" type="1" subject="null" body="Degerli musterimiz,26.04.2022 tarihinde 23:59'da kesilen fatura tutari 196 TL,son odeme tarihi 16.05.2022 dir.Bir sonraki faturaniz 26.05.2022 tarihinde kesilecektir.Faturalarinizi mobil hattinizdan 9333u UCRETSIZ arayarak veya pttcell.com.tr online islemlerden kredi kartinizla odeyebilirsiniz.Odeme yaptiysaniz bu mesaji dikkate almayiniz. B001" toa="null" sc_toa="null" service_center="+905598008000" read="1" status="-1" locked="0" date_sent="1651489728000" sub_id="2" readable_date="2 May 2022 14:08:51" contact_name="(Unknown)" />
  <sms protocol="0" address="+67976494926" date="1651499355624" type="1" subject="null" body="Villarreal v Liverpool yarin youwin de! 05111990 www.hepsibahis429.com da ilk transferinle 1200TLye kadar %100 kazan, Sampiyonlar Ligi bahislerini kacirma!" toa="null" sc_toa="null" service_center="+6797000009" read="1" status="-1" locked="0" date_sent="1651499351000" sub_id="2" readable_date="2 May 2022 16:49:15" contact_name="(Unknown)" />
  <sms protocol="0" address="+905339612317" date="1651502475054" type="2" subject="null" body="Bayramın mübarek olsun yengee&#129392;" toa="null" sc_toa="null" service_center="null" read="1" status="-1" locked="0" date_sent="0" sub_id="1" readable_date="2 May 2022 17:41:15" contact_name="Huriye Yenge" />
  <sms protocol="0" address="TOKATYILDIZ" date="1651510729802" type="1" subject="null" body="SN. ABDULKADIR YILDIZ, 4750199 PNR KODLU, 02-05-2022 21:45 ORDU - TRABZON, 5, 6, NOLU KOLTUK(LAR) REZERVE EDILMISTIR. REZERVASYONUNUZ 02-05-2022 21:45A KADAR GECERLIDIR. B002" toa="null" sc_toa="null" service_center="+905329065500" read="1" status="-1" locked="0" date_sent="1651509149000" sub_id="2" readable_date="2 May 2022 19:58:49" contact_name="(Unknown)" />
  <sms protocol="0" address="AKSA D.GAZ" date="1651558588338" type="1" subject="null" body="Sayin abonemiz, 3115678 nolu aboneliginize ait 5.5.2022 son odeme tarihli, 146,28 TL tutarli dogal gaz tuketim faturaniz olusturulmustur. AKSA DOGALGAZ B016" toa="null" sc_toa="null" service_center="+908503157003" read="1" status="-1" locked="0" date_sent="1651558586000" sub_id="2" readable_date="3 May 2022 09:16:28" contact_name="(Unknown)" />
  <sms protocol="0" address="+905359299441" date="1651600756620" type="1" subject="null" body="Agah hoca ben Aşırı yoğunluktan kabulum yok 0542 5726558 Zaid hocamızın numarasi selamımı söyleyin yardımcı olur" toa="null" sc_toa="null" service_center="+905598008000" read="1" status="-1" locked="0" date_sent="1651600756000" sub_id="1" readable_date="3 May 2022 20:59:16" contact_name="Zaid Hoca" />
  <sms protocol="0" address="+905488405956" date="1651644100046" type="1" subject="null" body="MAYIS AYI BOYUNCA HER GUN 1 KEZ %200 - 1.000 TL YATIRIM BONUSU HEDIYE ! ONWIN AILESI OLARAK BAYRAMINIZI EN ICTEN DILEKLERIMIZ ILE KUTLARIZ : www.onwin395.com" toa="null" sc_toa="null" service_center="+908504140500" read="0" status="-1" locked="0" date_sent="1651644100000" sub_id="1" readable_date="4 May 2022 09:01:40" contact_name="(Unknown)" />
  <sms protocol="0" address="KAMIL KOC" date="1651685746911" type="1" subject="null" body="Biletiniz onaylandı. &#10;PNR No: 3007981024&#10;Toplam fiyat: 240.00 TRY&#10;Ordu - Trabzon ??&#10;Kalkış: 04.05.22 23:20&#10;Koltuk: 39, 40&#10;Check-in için bilet&#10;&#10;https://mfb-fb-pdf-prod.s3.eu-central-1.amazonaws.com/o8yt5zni5xoso8ewwecew08werxhurso2ra08h4s2jc7v3hl21/FLIX-Ticket-3007981024.pdf. - B030" toa="null" sc_toa="null" service_center="+902122746329" read="1" status="-1" locked="0" date_sent="1651685732000" sub_id="1" readable_date="4 May 2022 20:35:46" contact_name="(Unknown)" />
  <sms protocol="0" address="KAMIL KOC" date="1651698981360" type="1" subject="null" body="Kullanıcı girişi için onay kodunuz:55759  . - B030" toa="null" sc_toa="null" service_center="+903124253896" read="1" status="-1" locked="0" date_sent="1651698979000" sub_id="1" readable_date="5 May 2022 00:16:21" contact_name="(Unknown)" />
  <sms protocol="0" address="FATURANET" date="1651745730995" type="1" subject="null" body="Degerli Musterimiz, 7028031694 nolu internet hizmetinizin 16/05/2022 son odeme tarihli faturasi 117,50 TL'dir. Odemenizi Online Islemler'i kullanarak guvenle yapabilirsiniz. https://onlineislemler.turktelekom.com.tr/legacy/genisbant/fatura-goruntuleme Odeme yapildiysa bu mesaji lutfen dikkate almayiniz. B001" toa="null" sc_toa="null" service_center="+905598008000" read="1" status="-1" locked="0" date_sent="1651745730000" sub_id="1" readable_date="5 May 2022 13:15:30" contact_name="(Unknown)" />
  <sms protocol="0" address="+905488429014" date="1651760901065" type="1" subject="null" body="MAYIS AYI BOYUNCA HER GUN %200 - 1.000 TL YATIRIM BONUS FIRSATI, CEKIM LIMITIMIZ ARTIK 250.000 TL! HER AYIN 5'INDE %50 1.000 TL YATIRIM BONUSU: www.onwin396.com" toa="null" sc_toa="null" service_center="+908504140500" read="0" status="-1" locked="0" date_sent="1651760901000" sub_id="1" readable_date="5 May 2022 17:28:21" contact_name="(Unknown)" />
  <sms protocol="0" address="9520" date="1651772095950" type="2" subject="null" body="SIFRE" toa="null" sc_toa="null" service_center="null" read="1" status="-1" locked="0" date_sent="0" sub_id="1" readable_date="5 May 2022 20:34:55" contact_name="(Unknown)" />
  <sms protocol="0" address="9520" date="1651772103239" type="1" subject="null" body="Online İşlemler için tek kullanımlık sifreniz: 986411. Sifrenizi kimseyle paylaşmayınız. B001" toa="null" sc_toa="null" service_center="+905598008000" read="1" status="-1" locked="0" date_sent="1651772103000" sub_id="1" readable_date="5 May 2022 20:35:03" contact_name="(Unknown)" />
  <sms protocol="0" address="HALKBANK." date="1651773107767" type="1" subject="null" body="Sonu 6347 olan kartınızla 0 USD tutarlı kart doğrulama işlemi gerçekleştirildi.Size ait değilse 08502220400'ü arayıp 0'ı tuşlayabilirsiniz. B016" toa="null" sc_toa="null" service_center="+908503157001" read="1" status="-1" locked="0" date_sent="1651773107000" sub_id="1" readable_date="5 May 2022 20:51:47" contact_name="(Unknown)" />
  <sms protocol="0" address="9230" date="1651773348113" type="1" subject="null" body="Sil Supur Kampanyasindan kazandiginiz Haftalik 5GB paketi hattiniza tanimlanmistir. B001" toa="null" sc_toa="null" service_center="+905598008000" read="1" status="-1" locked="0" date_sent="1651772137000" sub_id="1" readable_date="5 May 2022 20:55:48" contact_name="(Unknown)" />
  <sms protocol="0" address="A.O.ULUSOY" date="1651912264040" type="1" subject="null" body="SN. GAMZE YILDIZ, 8172332 PNR KODLU, 07-05-2022 11:30 TRABZON - ORDU, 2, 3, NOLU KOLTUK(LAR) SATIN ALINMISTIR. TOPLAM UCRET 180 TL B002" toa="null" sc_toa="null" service_center="+905329065500" read="1" status="-1" locked="0" date_sent="1651912264000" sub_id="1" readable_date="7 May 2022 11:31:04" contact_name="(Unknown)" />
  <sms protocol="0" address="TURKTELEKOM" date="1651914872688" type="1" subject="null" body="Degerli musterimiz, Sil Supur Haftalik 5 GB paketiniz mobil hattiniza tanimlanmistir. Paket kapsamindaki haklarinizi 13/05/2022'a kadar kullanabilirsiniz. B001" toa="null" sc_toa="null" service_center="+905598008000" read="1" status="-1" locked="0" date_sent="1651914872000" sub_id="1" readable_date="7 May 2022 12:14:32" contact_name="(Unknown)" />
  <sms protocol="0" address="WiBU" date="1651916332310" type="1" subject="null" body="code: 4902 kodu ile WiFiBurada'ya giris yapabilirsiniz.&#10;B273" toa="null" sc_toa="null" service_center="+908506660000" read="1" status="-1" locked="0" date_sent="1651916332000" sub_id="1" readable_date="7 May 2022 12:38:52" contact_name="(Unknown)" />
  <sms protocol="0" address="+905488627256" date="1652023324315" type="1" subject="null" body="HER GUN 1 YATIRIMA %200 - 1.000 TL YATIRIM BONUSU, %30 LIMITSIZ VE CEVRIMSIZ KAYIP BONUS, CEKIM LIMITIMIZI 250.000 TL OLARAK GUNCELLEDIK : www.onwin397.com" toa="null" sc_toa="null" service_center="+908504140500" read="0" status="-1" locked="0" date_sent="1652023324000" sub_id="1" readable_date="8 May 2022 18:22:04" contact_name="(Unknown)" />
  <sms protocol="0" address="+905076361887" date="1652093391860" type="2" subject="null" body="Ben Alp Ege'nin annesi gamze" toa="null" sc_toa="null" service_center="null" read="1" status="-1" locked="0" date_sent="0" sub_id="1" readable_date="9 May 2022 13:49:51" contact_name="Şeyma Ogrr" />
  <sms protocol="0" address="ILHAN DUMAN" date="1652098225666" type="1" subject="null" body="SN. A*** Y***, 54436838XX NOLU VODAFONE DOSYANIZA AIT 4087 TL BORCUNUZU SIZE OZEL FAIZ INDIRIMI ILE 3463 TL OLARAK ODEMEK ICIN SON GUN 13 MAYIS. KAMPANYADAN YARARLANMAK ICIN HEMEN ARAYINIZ. 02167094353 ILHAN-DUMAN AVUKATLIK ORTAKLIGI B016" toa="null" sc_toa="null" service_center="+908503157001" read="1" status="-1" locked="0" date_sent="1652098222000" sub_id="2" readable_date="9 May 2022 15:10:25" contact_name="(Unknown)" />
  <sms protocol="0" address="ON." date="1652108335700" type="1" subject="null" body="ON'lulara ozel Carrefour'dan 50 TL indirim! ON'lu ol, 31 Mayıs'a kadar yapacagin 100 TL ve uzeri alisverise 50TL indirim kazan! Musterimiz olmak icin: https://burgan.com.tr/on/b/Ag57Nin2 Bilgi icin:0850 222 29 10 Bankamizdan tanitim icerikli SMS almak istemiyorsan ON IPTAL yazip 3525'e ucretsiz gonderebilirsin.Mersis:0140003231000116  B016" toa="null" sc_toa="null" service_center="+908503157003" read="1" status="-1" locked="0" date_sent="1652108330000" sub_id="2" readable_date="9 May 2022 17:58:55" contact_name="(Unknown)" />
  <sms protocol="0" address="+905368715281" date="1652171659161" type="2" subject="null" body="Bana geri donermsiiniz hocam" toa="null" sc_toa="null" service_center="null" read="1" status="-1" locked="0" date_sent="0" sub_id="1" readable_date="10 May 2022 11:34:19" contact_name="Handanhoca" />
  <sms protocol="0" address="Yemeksepeti" date="1652195704523" type="1" subject="null" body="Maalesef Çorbacı Güzeli siparişinizi onaylamadı. Daha fazla seçenek keşfetmek için Yemeksepeti'ne girebilirsiniz. B043" toa="null" sc_toa="null" service_center="+908505701310" read="0" status="-1" locked="0" date_sent="1652205748000" sub_id="1" readable_date="10 May 2022 18:15:04" contact_name="(Unknown)" />
  <mms date="1650697100000" rr="129" sub="null" ct_t="application/vnd.wap.multipart.related" read_status="null" seen="1" msg_box="2" address="+905414311675" sub_cs="null" resp_st="null" retr_st="null" d_tm="null" text_only="1" exp="604800" locked="0" m_id="null" st="null" retr_txt_cs="null" retr_txt="null" creator="com.google.android.apps.messaging" date_sent="0" read="1" m_size="15" rpt_a="null" ct_cls="135" pri="129" sub_id="1" tr_id="proto:CkIKImNvbS5nb29nbGUuYW5kcm9pZC5hcHBzLm1lc3NhZ2luZy4SHBIaKhhNeDJvczc0cnp2U1Vta204aHlBcmhCU1E=" resp_txt="null" ct_l="null" m_cls="personal" d_rpt="129" v="18" service_center="null" _id="27" m_type="128" readable_date="23 Nis 2022 09:58:20" contact_name="Aydin">
    <parts>
      <part seq="-1" ct="application/smil" name="null" chset="null" cd="null" fn="null" cid="&lt;smil&gt;" cl="smil.xml" ctt_s="null" ctt_t="null" text='&lt;smil&gt;&lt;head&gt;&lt;layout&gt;&lt;root-layout/&gt;&lt;region id="Text" top="0" left="0" height="100%" width="100%"/&gt;&lt;/layout&gt;&lt;/head&gt;&lt;body&gt;&lt;par dur="5000ms"&gt;&lt;text src="text000001.txt" region="Text" /&gt;&lt;/par&gt;&lt;/body&gt;&lt;/smil&gt;' />
      <part seq="0" ct="text/plain" name="null" chset="106" cd="null" fn="null" cid="&lt;text000001&gt;" cl="text000001.txt" ctt_s="null" ctt_t="null" text="Bisey yok aydin" />
    </parts>
    <addrs>
      <addr address="insert-address-token" type="137" charset="106" />
      <addr address="+905414311675" type="151" charset="106" />
    </addrs>
  </mms>
  <mms date="1650697129000" rr="129" sub="null" ct_t="application/vnd.wap.multipart.related" read_status="null" seen="1" msg_box="2" address="+905414311675" sub_cs="null" resp_st="null" retr_st="null" d_tm="null" text_only="1" exp="604800" locked="0" m_id="null" st="null" retr_txt_cs="null" retr_txt="null" creator="com.google.android.apps.messaging" date_sent="0" read="1" m_size="22" rpt_a="null" ct_cls="135" pri="129" sub_id="1" tr_id="proto:CkIKImNvbS5nb29nbGUuYW5kcm9pZC5hcHBzLm1lc3NhZ2luZy4SHBIaKhhNeDVneEhONEJkUlFtZmlZUVlVenlXbmc=" resp_txt="null" ct_l="null" m_cls="personal" d_rpt="129" v="18" service_center="null" _id="28" m_type="128" readable_date="23 Nis 2022 09:58:49" contact_name="Aydin">
    <parts>
      <part seq="-1" ct="application/smil" name="null" chset="null" cd="null" fn="null" cid="&lt;smil&gt;" cl="smil.xml" ctt_s="null" ctt_t="null" text='&lt;smil&gt;&lt;head&gt;&lt;layout&gt;&lt;root-layout/&gt;&lt;region id="Text" top="0" left="0" height="100%" width="100%"/&gt;&lt;/layout&gt;&lt;/head&gt;&lt;body&gt;&lt;par dur="5000ms"&gt;&lt;text src="text000001.txt" region="Text" /&gt;&lt;/par&gt;&lt;/body&gt;&lt;/smil&gt;' />
      <part seq="0" ct="text/plain" name="null" chset="106" cd="null" fn="null" cid="&lt;text000001&gt;" cl="text000001.txt" ctt_s="null" ctt_t="null" text="Cocuklarin okulundayim" />
    </parts>
    <addrs>
      <addr address="insert-address-token" type="137" charset="106" />
      <addr address="+905414311675" type="151" charset="106" />
    </addrs>
  </mms>
  <mms date="1650697140000" rr="129" sub="null" ct_t="application/vnd.wap.multipart.related" read_status="null" seen="1" msg_box="2" address="+905414311675" sub_cs="null" resp_st="null" retr_st="null" d_tm="null" text_only="1" exp="604800" locked="0" m_id="null" st="null" retr_txt_cs="null" retr_txt="null" creator="com.google.android.apps.messaging" date_sent="0" read="1" m_size="17" rpt_a="null" ct_cls="135" pri="129" sub_id="1" tr_id="proto:CkIKImNvbS5nb29nbGUuYW5kcm9pZC5hcHBzLm1lc3NhZ2luZy4SHBIaKhhNeHVzMC1OdGJiUzktYTVBM0laSC1qaUE=" resp_txt="null" ct_l="null" m_cls="personal" d_rpt="129" v="18" service_center="null" _id="29" m_type="128" readable_date="23 Nis 2022 09:59:00" contact_name="Aydin">
    <parts>
      <part seq="-1" ct="application/smil" name="null" chset="null" cd="null" fn="null" cid="&lt;smil&gt;" cl="smil.xml" ctt_s="null" ctt_t="null" text='&lt;smil&gt;&lt;head&gt;&lt;layout&gt;&lt;root-layout/&gt;&lt;region id="Text" top="0" left="0" height="100%" width="100%"/&gt;&lt;/layout&gt;&lt;/head&gt;&lt;body&gt;&lt;par dur="5000ms"&gt;&lt;text src="text000001.txt" region="Text" /&gt;&lt;/par&gt;&lt;/body&gt;&lt;/smil&gt;' />
      <part seq="0" ct="text/plain" name="null" chset="106" cd="null" fn="null" cid="&lt;text000001&gt;" cl="text000001.txt" ctt_s="null" ctt_t="null" text="23 Nisan ya bugun" />
    </parts>
    <addrs>
      <addr address="insert-address-token" type="137" charset="106" />
      <addr address="+905414311675" type="151" charset="106" />
    </addrs>
  </mms>
  <mms date="1650697148000" rr="129" sub="null" ct_t="application/vnd.wap.multipart.related" read_status="null" seen="1" msg_box="2" address="+905414311675" sub_cs="null" resp_st="null" retr_st="null" d_tm="null" text_only="1" exp="604800" locked="0" m_id="null" st="null" retr_txt_cs="null" retr_txt="null" creator="com.google.android.apps.messaging" date_sent="0" read="1" m_size="14" rpt_a="null" ct_cls="135" pri="129" sub_id="1" tr_id="proto:CkIKImNvbS5nb29nbGUuYW5kcm9pZC5hcHBzLm1lc3NhZ2luZy4SHBIaKhhNeHdqeTlNVlVaU3Z1LWhQN25GZnVTakE=" resp_txt="null" ct_l="null" m_cls="personal" d_rpt="129" v="18" service_center="null" _id="30" m_type="128" readable_date="23 Nis 2022 09:59:08" contact_name="Aydin">
    <parts>
      <part seq="-1" ct="application/smil" name="null" chset="null" cd="null" fn="null" cid="&lt;smil&gt;" cl="smil.xml" ctt_s="null" ctt_t="null" text='&lt;smil&gt;&lt;head&gt;&lt;layout&gt;&lt;root-layout/&gt;&lt;region id="Text" top="0" left="0" height="100%" width="100%"/&gt;&lt;/layout&gt;&lt;/head&gt;&lt;body&gt;&lt;par dur="5000ms"&gt;&lt;text src="text000001.txt" region="Text" /&gt;&lt;/par&gt;&lt;/body&gt;&lt;/smil&gt;' />
      <part seq="0" ct="text/plain" name="null" chset="106" cd="null" fn="null" cid="&lt;text000001&gt;" cl="text000001.txt" ctt_s="null" ctt_t="null" text="Onlari izliyrm" />
    </parts>
    <addrs>
      <addr address="insert-address-token" type="137" charset="106" />
      <addr address="+905414311675" type="151" charset="106" />
    </addrs>
  </mms>
  <mms date="1651342903000" rr="129" sub="null" ct_t="application/vnd.wap.multipart.related" read_status="null" seen="1" msg_box="2" address="+905414311675" sub_cs="null" resp_st="null" retr_st="null" d_tm="null" text_only="1" exp="604800" locked="0" m_id="null" st="null" retr_txt_cs="null" retr_txt="null" creator="com.google.android.apps.messaging" date_sent="0" read="1" m_size="21" rpt_a="null" ct_cls="135" pri="129" sub_id="1" tr_id="proto:CkIKImNvbS5nb29nbGUuYW5kcm9pZC5hcHBzLm1lc3NhZ2luZy4SHBIaKhhNeHBldXQ0eE9uVFlXZzFmQmswVWN5cEE=" resp_txt="null" ct_l="null" m_cls="personal" d_rpt="129" v="18" service_center="null" _id="36" m_type="128" readable_date="30 Nis 2022 21:21:43" contact_name="Aydin">
    <parts>
      <part seq="-1" ct="application/smil" name="null" chset="null" cd="null" fn="null" cid="&lt;smil&gt;" cl="smil.xml" ctt_s="null" ctt_t="null" text='&lt;smil&gt;&lt;head&gt;&lt;layout&gt;&lt;root-layout/&gt;&lt;region id="Text" top="0" left="0" height="100%" width="100%"/&gt;&lt;/layout&gt;&lt;/head&gt;&lt;body&gt;&lt;par dur="5000ms"&gt;&lt;text src="text000001.txt" region="Text" /&gt;&lt;/par&gt;&lt;/body&gt;&lt;/smil&gt;' />
      <part seq="0" ct="text/plain" name="null" chset="106" cd="null" fn="null" cid="&lt;text000001&gt;" cl="text000001.txt" ctt_s="null" ctt_t="null" text="Müşterilere bakiyom" />
    </parts>
    <addrs>
      <addr address="insert-address-token" type="137" charset="106" />
      <addr address="+905414311675" type="151" charset="106" />
    </addrs>
  </mms>
  <mms date="1651342916000" rr="129" sub="null" ct_t="application/vnd.wap.multipart.related" read_status="null" seen="1" msg_box="2" address="+905414311675" sub_cs="null" resp_st="null" retr_st="null" d_tm="null" text_only="1" exp="604800" locked="0" m_id="null" st="null" retr_txt_cs="null" retr_txt="null" creator="com.google.android.apps.messaging" date_sent="0" read="1" m_size="20" rpt_a="null" ct_cls="135" pri="129" sub_id="1" tr_id="proto:CkIKImNvbS5nb29nbGUuYW5kcm9pZC5hcHBzLm1lc3NhZ2luZy4SHBIaKhhNeEJleUlUN2Q5U1dDbGJGbUxtRzc5UHc=" resp_txt="null" ct_l="null" m_cls="personal" d_rpt="129" v="18" service_center="null" _id="37" m_type="128" readable_date="30 Nis 2022 21:21:56" contact_name="Aydin">
    <parts>
      <part seq="-1" ct="application/smil" name="null" chset="null" cd="null" fn="null" cid="&lt;smil&gt;" cl="smil.xml" ctt_s="null" ctt_t="null" text='&lt;smil&gt;&lt;head&gt;&lt;layout&gt;&lt;root-layout/&gt;&lt;region id="Text" top="0" left="0" height="100%" width="100%"/&gt;&lt;/layout&gt;&lt;/head&gt;&lt;body&gt;&lt;par dur="5000ms"&gt;&lt;text src="text000001.txt" region="Text" /&gt;&lt;/par&gt;&lt;/body&gt;&lt;/smil&gt;' />
      <part seq="0" ct="text/plain" name="null" chset="106" cd="null" fn="null" cid="&lt;text000001&gt;" cl="text000001.txt" ctt_s="null" ctt_t="null" text="Boş kaliyim yazarim" />
    </parts>
    <addrs>
      <addr address="insert-address-token" type="137" charset="106" />
      <addr address="+905414311675" type="151" charset="106" />
    </addrs>
  </mms>
  <mms date="1651346762000" rr="129" sub="null" ct_t="application/vnd.wap.multipart.related" read_status="null" seen="1" msg_box="2" address="+905387326287" sub_cs="null" resp_st="null" retr_st="null" d_tm="null" text_only="1" exp="604800" locked="0" m_id="null" st="null" retr_txt_cs="null" retr_txt="null" creator="com.google.android.apps.messaging" date_sent="0" read="1" m_size="55" rpt_a="null" ct_cls="135" pri="129" sub_id="1" tr_id="proto:CkIKImNvbS5nb29nbGUuYW5kcm9pZC5hcHBzLm1lc3NhZ2luZy4SHBIaKhhNeGJWZnBDZGhlVEN1V1NTQ3NLVXhQVEE=" resp_txt="null" ct_l="null" m_cls="personal" d_rpt="129" v="18" service_center="null" _id="38" m_type="128" readable_date="30 Nis 2022 22:26:02" contact_name="Şahane Döner">
    <parts>
      <part seq="-1" ct="application/smil" name="null" chset="null" cd="null" fn="null" cid="&lt;smil&gt;" cl="smil.xml" ctt_s="null" ctt_t="null" text='&lt;smil&gt;&lt;head&gt;&lt;layout&gt;&lt;root-layout/&gt;&lt;region id="Text" top="0" left="0" height="100%" width="100%"/&gt;&lt;/layout&gt;&lt;/head&gt;&lt;body&gt;&lt;par dur="5000ms"&gt;&lt;text src="text000001.txt" region="Text" /&gt;&lt;/par&gt;&lt;/body&gt;&lt;/smil&gt;' />
      <part seq="0" ct="text/plain" name="null" chset="106" cd="null" fn="null" cid="&lt;text000001&gt;" cl="text000001.txt" ctt_s="null" ctt_t="null" text="Tras olcaksan yarın gel kanka bugün çakılı doluyum" />
    </parts>
    <addrs>
      <addr address="insert-address-token" type="137" charset="106" />
      <addr address="+905387326287" type="151" charset="106" />
    </addrs>
  </mms>
  <mms date="1651346766000" rr="129" sub="null" ct_t="application/vnd.wap.multipart.related" read_status="null" seen="1" msg_box="2" address="+905387326287" sub_cs="null" resp_st="null" retr_st="null" d_tm="null" text_only="1" exp="604800" locked="0" m_id="null" st="null" retr_txt_cs="null" retr_txt="null" creator="com.google.android.apps.messaging" date_sent="0" read="1" m_size="9" rpt_a="null" ct_cls="135" pri="129" sub_id="1" tr_id="proto:CkIKImNvbS5nb29nbGUuYW5kcm9pZC5hcHBzLm1lc3NhZ2luZy4SHBIaKhhNeDhNYU5NeC1aUUx5SGxUSTRlVGtkOWc=" resp_txt="null" ct_l="null" m_cls="personal" d_rpt="129" v="18" service_center="null" _id="39" m_type="128" readable_date="30 Nis 2022 22:26:06" contact_name="Şahane Döner">
    <parts>
      <part seq="-1" ct="application/smil" name="null" chset="null" cd="null" fn="null" cid="&lt;smil&gt;" cl="smil.xml" ctt_s="null" ctt_t="null" text='&lt;smil&gt;&lt;head&gt;&lt;layout&gt;&lt;root-layout/&gt;&lt;region id="Text" top="0" left="0" height="100%" width="100%"/&gt;&lt;/layout&gt;&lt;/head&gt;&lt;body&gt;&lt;par dur="5000ms"&gt;&lt;text src="text000001.txt" region="Text" /&gt;&lt;/par&gt;&lt;/body&gt;&lt;/smil&gt;' />
      <part seq="0" ct="text/plain" name="null" chset="106" cd="null" fn="null" cid="&lt;text000001&gt;" cl="text000001.txt" ctt_s="null" ctt_t="null" text="Yerim yok" />
    </parts>
    <addrs>
      <addr address="insert-address-token" type="137" charset="106" />
      <addr address="+905387326287" type="151" charset="106" />
    </addrs>
  </mms>
  <mms date="1651351648000" rr="129" sub="null" ct_t="application/vnd.wap.multipart.related" read_status="null" seen="1" msg_box="2" address="+905387326287" sub_cs="null" resp_st="null" retr_st="null" d_tm="null" text_only="1" exp="604800" locked="0" m_id="null" st="null" retr_txt_cs="null" retr_txt="null" creator="com.google.android.apps.messaging" date_sent="0" read="1" m_size="5" rpt_a="null" ct_cls="135" pri="129" sub_id="1" tr_id="proto:CkIKImNvbS5nb29nbGUuYW5kcm9pZC5hcHBzLm1lc3NhZ2luZy4SHBIaKhhNeDZJcy1La0ZIUj1PMmlCeXR5UW94a0E=" resp_txt="null" ct_l="null" m_cls="personal" d_rpt="129" v="18" service_center="null" _id="40" m_type="128" readable_date="30 Nis 2022 23:47:28" contact_name="Şahane Döner">
    <parts>
      <part seq="-1" ct="application/smil" name="null" chset="null" cd="null" fn="null" cid="&lt;smil&gt;" cl="smil.xml" ctt_s="null" ctt_t="null" text='&lt;smil&gt;&lt;head&gt;&lt;layout&gt;&lt;root-layout/&gt;&lt;region id="Text" top="0" left="0" height="100%" width="100%"/&gt;&lt;/layout&gt;&lt;/head&gt;&lt;body&gt;&lt;par dur="5000ms"&gt;&lt;text src="text000001.txt" region="Text" /&gt;&lt;/par&gt;&lt;/body&gt;&lt;/smil&gt;' />
      <part seq="0" ct="text/plain" name="null" chset="106" cd="null" fn="null" cid="&lt;text000001&gt;" cl="text000001.txt" ctt_s="null" ctt_t="null" text="Ahmet" />
    </parts>
    <addrs>
      <addr address="insert-address-token" type="137" charset="106" />
      <addr address="+905387326287" type="151" charset="106" />
    </addrs>
  </mms>
  <mms date="1651351671000" rr="129" sub="null" ct_t="application/vnd.wap.multipart.related" read_status="null" seen="1" msg_box="2" address="+905387326287" sub_cs="null" resp_st="null" retr_st="null" d_tm="null" text_only="1" exp="604800" locked="0" m_id="null" st="null" retr_txt_cs="null" retr_txt="null" creator="com.google.android.apps.messaging" date_sent="0" read="1" m_size="22" rpt_a="null" ct_cls="135" pri="129" sub_id="1" tr_id="proto:CkIKImNvbS5nb29nbGUuYW5kcm9pZC5hcHBzLm1lc3NhZ2luZy4SHBIaKhhNeHd1ek9RNHJ4UlZTZXVQQU1RMG81MkE=" resp_txt="null" ct_l="null" m_cls="personal" d_rpt="129" v="18" service_center="null" _id="41" m_type="128" readable_date="30 Nis 2022 23:47:51" contact_name="Şahane Döner">
    <parts>
      <part seq="-1" ct="application/smil" name="null" chset="null" cd="null" fn="null" cid="&lt;smil&gt;" cl="smil.xml" ctt_s="null" ctt_t="null" text='&lt;smil&gt;&lt;head&gt;&lt;layout&gt;&lt;root-layout/&gt;&lt;region id="Text" top="0" left="0" height="100%" width="100%"/&gt;&lt;/layout&gt;&lt;/head&gt;&lt;body&gt;&lt;par dur="5000ms"&gt;&lt;text src="text000001.txt" region="Text" /&gt;&lt;/par&gt;&lt;/body&gt;&lt;/smil&gt;' />
      <part seq="0" ct="text/plain" name="null" chset="106" cd="null" fn="null" cid="&lt;text000001&gt;" cl="text000001.txt" ctt_s="null" ctt_t="null" text="Yarın 1e yazdım seni" />
    </parts>
    <addrs>
      <addr address="insert-address-token" type="137" charset="106" />
      <addr address="+905387326287" type="151" charset="106" />
    </addrs>
  </mms>
  <mms date="1651351683000" rr="129" sub="null" ct_t="application/vnd.wap.multipart.related" read_status="null" seen="1" msg_box="2" address="+905387326287" sub_cs="null" resp_st="null" retr_st="null" d_tm="null" text_only="1" exp="604800" locked="0" m_id="null" st="null" retr_txt_cs="null" retr_txt="null" creator="com.google.android.apps.messaging" date_sent="0" read="1" m_size="8" rpt_a="null" ct_cls="135" pri="129" sub_id="1" tr_id="proto:CkIKImNvbS5nb29nbGUuYW5kcm9pZC5hcHBzLm1lc3NhZ2luZy4SHBIaKhhNeDR5RkpqdnE1VGhPRU85RDNiTGN1WlE=" resp_txt="null" ct_l="null" m_cls="personal" d_rpt="129" v="18" service_center="null" _id="42" m_type="128" readable_date="30 Nis 2022 23:48:03" contact_name="Şahane Döner">
    <parts>
      <part seq="-1" ct="application/smil" name="null" chset="null" cd="null" fn="null" cid="&lt;smil&gt;" cl="smil.xml" ctt_s="null" ctt_t="null" text='&lt;smil&gt;&lt;head&gt;&lt;layout&gt;&lt;root-layout/&gt;&lt;region id="Text" top="0" left="0" height="100%" width="100%"/&gt;&lt;/layout&gt;&lt;/head&gt;&lt;body&gt;&lt;par dur="5000ms"&gt;&lt;text src="text000001.txt" region="Text" /&gt;&lt;/par&gt;&lt;/body&gt;&lt;/smil&gt;' />
      <part seq="0" ct="text/plain" name="null" chset="106" cd="null" fn="null" cid="&lt;text000001&gt;" cl="text000001.txt" ctt_s="null" ctt_t="null" text="1 de gel" />
    </parts>
    <addrs>
      <addr address="insert-address-token" type="137" charset="106" />
      <addr address="+905387326287" type="151" charset="106" />
    </addrs>
  </mms>
  <mms date="1651351703000" rr="null" sub="" ct_t="text/plain" read_status="null" seen="1" msg_box="1" address="+905387326287" sub_cs="106" resp_st="null" retr_st="null" d_tm="null" text_only="1" exp="null" locked="0" m_id="null" st="null" retr_txt_cs="null" retr_txt="null" creator="com.google.android.apps.messaging" date_sent="1651351703" read="1" m_size="0" rpt_a="null" ct_cls="135" pri="null" sub_id="1" tr_id="proto:CkIKImNvbS5nb29nbGUuYW5kcm9pZC5hcHBzLm1lc3NhZ2luZy4SHBIaKhhNeGQ9NEI1MzFYUXQtY2pHQjJJbXdjaGc=" resp_txt="null" ct_l="null" m_cls="null" d_rpt="null" v="null" service_center="null" _id="43" m_type="132" readable_date="30 Nis 2022 23:48:23" contact_name="Şahane Döner">
    <parts>
      <part seq="0" ct="text/plain" name="body" chset="null" cd="null" fn="null" cid="null" cl="null" ctt_s="null" ctt_t="null" text="Kaçta acican sen " />
    </parts>
    <addrs>
      <addr address="+905387326287" type="130" charset="106" />
      <addr address="+905387326287" type="137" charset="106" />
      <addr address="+905524728860" type="151" charset="106" />
    </addrs>
  </mms>
  <mms date="1651351725000" rr="null" sub="" ct_t="text/plain" read_status="null" seen="1" msg_box="1" address="+905387326287" sub_cs="106" resp_st="null" retr_st="null" d_tm="null" text_only="1" exp="null" locked="0" m_id="null" st="null" retr_txt_cs="null" retr_txt="null" creator="com.google.android.apps.messaging" date_sent="1651351725" read="1" m_size="0" rpt_a="null" ct_cls="135" pri="null" sub_id="1" tr_id="proto:CkIKImNvbS5nb29nbGUuYW5kcm9pZC5hcHBzLm1lc3NhZ2luZy4SHBIaKhhNeDd1UDFTUjQ2Um8yRFNSak1KMk9xOVE=" resp_txt="null" ct_l="null" m_cls="null" d_rpt="null" v="null" service_center="null" _id="44" m_type="132" readable_date="30 Nis 2022 23:48:45" contact_name="Şahane Döner">
    <parts>
      <part seq="0" ct="text/plain" name="body" chset="null" cd="null" fn="null" cid="null" cl="null" ctt_s="null" ctt_t="null" text="Akşama yaz bana " />
    </parts>
    <addrs>
      <addr address="+905387326287" type="130" charset="106" />
      <addr address="+905387326287" type="137" charset="106" />
      <addr address="+905524728860" type="151" charset="106" />
    </addrs>
  </mms>
  <mms date="1651351769000" rr="129" sub="null" ct_t="application/vnd.wap.multipart.related" read_status="null" seen="1" msg_box="2" address="+905387326287" sub_cs="null" resp_st="null" retr_st="null" d_tm="null" text_only="1" exp="604800" locked="0" m_id="null" st="null" retr_txt_cs="null" retr_txt="null" creator="com.google.android.apps.messaging" date_sent="0" read="1" m_size="27" rpt_a="null" ct_cls="135" pri="129" sub_id="1" tr_id="proto:CkIKImNvbS5nb29nbGUuYW5kcm9pZC5hcHBzLm1lc3NhZ2luZy4SHBIaKhhNeGdGU29sSS1LUnpXQlZQVk1Ybm51a2c=" resp_txt="null" ct_l="null" m_cls="personal" d_rpt="129" v="18" service_center="null" _id="45" m_type="128" readable_date="30 Nis 2022 23:49:29" contact_name="Şahane Döner">
    <parts>
      <part seq="-1" ct="application/smil" name="null" chset="null" cd="null" fn="null" cid="&lt;smil&gt;" cl="smil.xml" ctt_s="null" ctt_t="null" text='&lt;smil&gt;&lt;head&gt;&lt;layout&gt;&lt;root-layout/&gt;&lt;region id="Text" top="0" left="0" height="100%" width="100%"/&gt;&lt;/layout&gt;&lt;/head&gt;&lt;body&gt;&lt;par dur="5000ms"&gt;&lt;text src="text000001.txt" region="Text" /&gt;&lt;/par&gt;&lt;/body&gt;&lt;/smil&gt;' />
      <part seq="0" ct="text/plain" name="null" chset="106" cd="null" fn="null" cid="&lt;text000001&gt;" cl="text000001.txt" ctt_s="null" ctt_t="null" text="Kaç istiyon akşam 6 iyimi" />
    </parts>
    <addrs>
      <addr address="insert-address-token" type="137" charset="106" />
      <addr address="+905387326287" type="151" charset="106" />
    </addrs>
  </mms>
  <mms date="1651351791000" rr="null" sub="" ct_t="text/plain" read_status="null" seen="1" msg_box="1" address="+905387326287" sub_cs="106" resp_st="null" retr_st="null" d_tm="null" text_only="1" exp="null" locked="0" m_id="null" st="null" retr_txt_cs="null" retr_txt="null" creator="com.google.android.apps.messaging" date_sent="1651351791" read="1" m_size="0" rpt_a="null" ct_cls="135" pri="null" sub_id="1" tr_id="proto:CkIKImNvbS5nb29nbGUuYW5kcm9pZC5hcHBzLm1lc3NhZ2luZy4SHBIaKhhNeEljVFZnWj10UVhLdWRSc3dhb0xmSUE=" resp_txt="null" ct_l="null" m_cls="null" d_rpt="null" v="null" service_center="null" _id="46" m_type="132" readable_date="30 Nis 2022 23:49:51" contact_name="Şahane Döner">
    <parts>
      <part seq="0" ct="text/plain" name="body" chset="null" cd="null" fn="null" cid="null" cl="null" ctt_s="null" ctt_t="null" text="Kapanışa yaz en son bana işte " />
    </parts>
    <addrs>
      <addr address="+905387326287" type="130" charset="106" />
      <addr address="+905387326287" type="137" charset="106" />
      <addr address="+905524728860" type="151" charset="106" />
    </addrs>
  </mms>
  <mms date="1651351802000" rr="129" sub="null" ct_t="application/vnd.wap.multipart.related" read_status="null" seen="1" msg_box="2" address="+905387326287" sub_cs="null" resp_st="null" retr_st="null" d_tm="null" text_only="1" exp="604800" locked="0" m_id="null" st="null" retr_txt_cs="null" retr_txt="null" creator="com.google.android.apps.messaging" date_sent="0" read="1" m_size="5" rpt_a="null" ct_cls="135" pri="129" sub_id="1" tr_id="proto:CkIKImNvbS5nb29nbGUuYW5kcm9pZC5hcHBzLm1lc3NhZ2luZy4SHBIaKhhNeFFGTTNrclBJUkR5PVhoMHE4aHhBQnc=" resp_txt="null" ct_l="null" m_cls="personal" d_rpt="129" v="18" service_center="null" _id="47" m_type="128" readable_date="30 Nis 2022 23:50:02" contact_name="Şahane Döner">
    <parts>
      <part seq="-1" ct="application/smil" name="null" chset="null" cd="null" fn="null" cid="&lt;smil&gt;" cl="smil.xml" ctt_s="null" ctt_t="null" text='&lt;smil&gt;&lt;head&gt;&lt;layout&gt;&lt;root-layout/&gt;&lt;region id="Text" top="0" left="0" height="100%" width="100%"/&gt;&lt;/layout&gt;&lt;/head&gt;&lt;body&gt;&lt;par dur="5000ms"&gt;&lt;text src="text000001.txt" region="Text" /&gt;&lt;/par&gt;&lt;/body&gt;&lt;/smil&gt;' />
      <part seq="0" ct="text/plain" name="null" chset="106" cd="null" fn="null" cid="&lt;text000001&gt;" cl="text000001.txt" ctt_s="null" ctt_t="null" text="Tamam" />
    </parts>
    <addrs>
      <addr address="insert-address-token" type="137" charset="106" />
      <addr address="+905387326287" type="151" charset="106" />
    </addrs>
  </mms>
  <mms date="1651670010000" rr="129" sub="null" ct_t="application/vnd.wap.multipart.related" read_status="null" seen="1" msg_box="2" address="+905551749100" sub_cs="null" resp_st="null" retr_st="null" d_tm="null" text_only="1" exp="604800" locked="0" m_id="null" st="null" retr_txt_cs="null" retr_txt="null" creator="com.google.android.apps.messaging" date_sent="0" read="1" m_size="16" rpt_a="null" ct_cls="135" pri="129" sub_id="1" tr_id="proto:CkIKImNvbS5nb29nbGUuYW5kcm9pZC5hcHBzLm1lc3NhZ2luZy4SHBIaKhhNeGZWQXowQ0VIUW1xR1hyMGpwV0NENFE=" resp_txt="null" ct_l="null" m_cls="personal" d_rpt="129" v="18" service_center="null" _id="48" m_type="128" readable_date="4 May 2022 16:13:30" contact_name="Kadir">
    <parts>
      <part seq="-1" ct="application/smil" name="null" chset="null" cd="null" fn="null" cid="&lt;smil&gt;" cl="smil.xml" ctt_s="null" ctt_t="null" text='&lt;smil&gt;&lt;head&gt;&lt;layout&gt;&lt;root-layout/&gt;&lt;region id="Text" top="0" left="0" height="100%" width="100%"/&gt;&lt;/layout&gt;&lt;/head&gt;&lt;body&gt;&lt;par dur="5000ms"&gt;&lt;text src="text000001.txt" region="Text" /&gt;&lt;/par&gt;&lt;/body&gt;&lt;/smil&gt;' />
      <part seq="0" ct="text/plain" name="null" chset="106" cd="null" fn="null" cid="&lt;text000001&gt;" cl="text000001.txt" ctt_s="null" ctt_t="null" text="Dahamusteri alma" />
    </parts>
    <addrs>
      <addr address="insert-address-token" type="137" charset="106" />
      <addr address="+905551749100" type="151" charset="106" />
    </addrs>
  </mms>
  <mms date="1651670019000" rr="129" sub="null" ct_t="application/vnd.wap.multipart.related" read_status="null" seen="1" msg_box="2" address="+905551749100" sub_cs="null" resp_st="null" retr_st="null" d_tm="null" text_only="1" exp="604800" locked="0" m_id="null" st="null" retr_txt_cs="null" retr_txt="null" creator="com.google.android.apps.messaging" date_sent="0" read="1" m_size="9" rpt_a="null" ct_cls="135" pri="129" sub_id="1" tr_id="proto:CkIKImNvbS5nb29nbGUuYW5kcm9pZC5hcHBzLm1lc3NhZ2luZy4SHBIaKhhNeGtVSTFNNVRLUXBpNUhOczlyRktUVVE=" resp_txt="null" ct_l="null" m_cls="personal" d_rpt="129" v="18" service_center="null" _id="49" m_type="128" readable_date="4 May 2022 16:13:39" contact_name="Kadir">
    <parts>
      <part seq="-1" ct="application/smil" name="null" chset="null" cd="null" fn="null" cid="&lt;smil&gt;" cl="smil.xml" ctt_s="null" ctt_t="null" text='&lt;smil&gt;&lt;head&gt;&lt;layout&gt;&lt;root-layout/&gt;&lt;region id="Text" top="0" left="0" height="100%" width="100%"/&gt;&lt;/layout&gt;&lt;/head&gt;&lt;body&gt;&lt;par dur="5000ms"&gt;&lt;text src="text000001.txt" region="Text" /&gt;&lt;/par&gt;&lt;/body&gt;&lt;/smil&gt;' />
      <part seq="0" ct="text/plain" name="null" chset="106" cd="null" fn="null" cid="&lt;text000001&gt;" cl="text000001.txt" ctt_s="null" ctt_t="null" text="Gecikiriz" />
    </parts>
    <addrs>
      <addr address="insert-address-token" type="137" charset="106" />
      <addr address="+905551749100" type="151" charset="106" />
    </addrs>
  </mms>
  <mms date="1651670042000" rr="129" sub="null" ct_t="application/vnd.wap.multipart.related" read_status="null" seen="1" msg_box="2" address="+905551749100" sub_cs="null" resp_st="null" retr_st="null" d_tm="null" text_only="1" exp="604800" locked="0" m_id="null" st="null" retr_txt_cs="null" retr_txt="null" creator="com.google.android.apps.messaging" date_sent="0" read="1" m_size="10" rpt_a="null" ct_cls="135" pri="129" sub_id="1" tr_id="proto:CkIKImNvbS5nb29nbGUuYW5kcm9pZC5hcHBzLm1lc3NhZ2luZy4SHBIaKhhNeGpLNUpEZWRGUWdTbHhQYi1OOXRzSmc=" resp_txt="null" ct_l="null" m_cls="personal" d_rpt="129" v="18" service_center="null" _id="50" m_type="128" readable_date="4 May 2022 16:14:02" contact_name="Kadir">
    <parts>
      <part seq="-1" ct="application/smil" name="null" chset="null" cd="null" fn="null" cid="&lt;smil&gt;" cl="smil.xml" ctt_s="null" ctt_t="null" text='&lt;smil&gt;&lt;head&gt;&lt;layout&gt;&lt;root-layout/&gt;&lt;region id="Text" top="0" left="0" height="100%" width="100%"/&gt;&lt;/layout&gt;&lt;/head&gt;&lt;body&gt;&lt;par dur="5000ms"&gt;&lt;text src="text000001.txt" region="Text" /&gt;&lt;/par&gt;&lt;/body&gt;&lt;/smil&gt;' />
      <part seq="0" ct="text/plain" name="null" chset="106" cd="null" fn="null" cid="&lt;text000001&gt;" cl="text000001.txt" ctt_s="null" ctt_t="null" text="Bide acele" />
    </parts>
    <addrs>
      <addr address="insert-address-token" type="137" charset="106" />
      <addr address="+905551749100" type="151" charset="106" />
    </addrs>
  </mms>
  <mms date="1651670045000" rr="129" sub="null" ct_t="application/vnd.wap.multipart.related" read_status="null" seen="1" msg_box="2" address="+905551749100" sub_cs="null" resp_st="null" retr_st="null" d_tm="null" text_only="1" exp="604800" locked="0" m_id="null" st="null" retr_txt_cs="null" retr_txt="null" creator="com.google.android.apps.messaging" date_sent="0" read="1" m_size="8" rpt_a="null" ct_cls="135" pri="129" sub_id="1" tr_id="proto:CkIKImNvbS5nb29nbGUuYW5kcm9pZC5hcHBzLm1lc3NhZ2luZy4SHBIaKhhNeDFid2xTRlhoUlpDS1ZBem8xYllSMXc=" resp_txt="null" ct_l="null" m_cls="personal" d_rpt="129" v="18" service_center="null" _id="51" m_type="128" readable_date="4 May 2022 16:14:05" contact_name="Kadir">
    <parts>
      <part seq="-1" ct="application/smil" name="null" chset="null" cd="null" fn="null" cid="&lt;smil&gt;" cl="smil.xml" ctt_s="null" ctt_t="null" text='&lt;smil&gt;&lt;head&gt;&lt;layout&gt;&lt;root-layout/&gt;&lt;region id="Text" top="0" left="0" height="100%" width="100%"/&gt;&lt;/layout&gt;&lt;/head&gt;&lt;body&gt;&lt;par dur="5000ms"&gt;&lt;text src="text000001.txt" region="Text" /&gt;&lt;/par&gt;&lt;/body&gt;&lt;/smil&gt;' />
      <part seq="0" ct="text/plain" name="null" chset="106" cd="null" fn="null" cid="&lt;text000001&gt;" cl="text000001.txt" ctt_s="null" ctt_t="null" text="Et biraz" />
    </parts>
    <addrs>
      <addr address="insert-address-token" type="137" charset="106" />
      <addr address="+905551749100" type="151" charset="106" />
    </addrs>
  </mms>
  <mms date="1652168632000" rr="129" sub="null" ct_t="application/vnd.wap.multipart.related" read_status="null" seen="1" msg_box="2" address="05076361887" sub_cs="null" resp_st="null" retr_st="null" d_tm="null" text_only="1" exp="604800" locked="0" m_id="null" st="null" retr_txt_cs="null" retr_txt="null" creator="com.google.android.apps.messaging" date_sent="0" read="1" m_size="45" rpt_a="null" ct_cls="135" pri="129" sub_id="1" tr_id="proto:CkIKImNvbS5nb29nbGUuYW5kcm9pZC5hcHBzLm1lc3NhZ2luZy4SHBIaKhhNeDBncXdtaTNiUXNxM3I1aS1aUm5JLVE=" resp_txt="null" ct_l="null" m_cls="personal" d_rpt="129" v="18" service_center="null" _id="53" m_type="128" readable_date="10 May 2022 10:43:52" contact_name="Şeyma Ogrr">
    <parts>
      <part seq="-1" ct="application/smil" name="null" chset="null" cd="null" fn="null" cid="&lt;smil&gt;" cl="smil.xml" ctt_s="null" ctt_t="null" text='&lt;smil&gt;&lt;head&gt;&lt;layout&gt;&lt;root-layout/&gt;&lt;region id="Text" top="0" left="0" height="100%" width="100%"/&gt;&lt;/layout&gt;&lt;/head&gt;&lt;body&gt;&lt;par dur="5000ms"&gt;&lt;text src="text000001.txt" region="Text" /&gt;&lt;/par&gt;&lt;/body&gt;&lt;/smil&gt;' />
      <part seq="0" ct="text/plain" name="null" chset="106" cd="null" fn="null" cid="&lt;text000001&gt;" cl="text000001.txt" ctt_s="null" ctt_t="null" text="Bana besleme listesini atarmisiniz rica etsem" />
    </parts>
    <addrs>
      <addr address="insert-address-token" type="137" charset="106" />
      <addr address="+905076361887" type="151" charset="106" />
    </addrs>
  </mms>
</smses>